Workbook
Name ASIENTO_FAC_COMPRA_1: 'LIBRO DIARIO'!$A$9
Name ASIENTO_FAC_COMPRA_10: 'LIBRO DIARIO'!$A$64
Name ASIENTO_FAC_COMPRA_11: 'LIBRO DIARIO'!$A$69
Name ASIENTO_FAC_COMPRA_12: 'LIBRO DIARIO'!$A$76
Name ASIENTO_FAC_COMPRA_13: 'LIBRO DIARIO'!$A$81
Name ASIENTO_FAC_COMPRA_14: 'LIBRO DIARIO'!$A$86
Name ASIENTO_FAC_COMPRA_15: 'LIBRO DIARIO'!$A$93
Name ASIENTO_FAC_COMPRA_16: 'LIBRO DIARIO'!$A$100
Name ASIENTO_FAC_COMPRA_17: 'LIBRO DIARIO'!$A$107
Name ASIENTO_FAC_COMPRA_18: 'LIBRO DIARIO'!$A$116
Name ASIENTO_FAC_COMPRA_19: 'LIBRO DIARIO'!$A$123
Name ASIENTO_FAC_COMPRA_2: 'LIBRO DIARIO'!$A$14
Name ASIENTO_FAC_COMPRA_20: 'LIBRO DIARIO'!$A$126
Name ASIENTO_FAC_COMPRA_21: 'LIBRO DIARIO'!$A$131
Name ASIENTO_FAC_COMPRA_22: 'LIBRO DIARIO'!$A$136
Name ASIENTO_FAC_COMPRA_23: 'LIBRO DIARIO'!$A$141
Name ASIENTO_FAC_COMPRA_24: 'LIBRO DIARIO'!$A$148
Name ASIENTO_FAC_COMPRA_25: 'LIBRO DIARIO'!$A$153
Name ASIENTO_FAC_COMPRA_26: 'LIBRO DIARIO'!$A$159
Name ASIENTO_FAC_COMPRA_27: 'LIBRO DIARIO'!$A$167
Name ASIENTO_FAC_COMPRA_28: 'LIBRO DIARIO'!$A$175
Name ASIENTO_FAC_COMPRA_29: 'LIBRO DIARIO'!$A$183
Name ASIENTO_FAC_COMPRA_3: 'LIBRO DIARIO'!$A$21
Name ASIENTO_FAC_COMPRA_30: 'LIBRO DIARIO'!$A$193
Name ASIENTO_FAC_COMPRA_31: 'LIBRO DIARIO'!$A$201
Name ASIENTO_FAC_COMPRA_32: 'LIBRO DIARIO'!$A$205
Name ASIENTO_FAC_COMPRA_33: 'LIBRO DIARIO'!$A$211
Name ASIENTO_FAC_COMPRA_34: 'LIBRO DIARIO'!$A$217
Name ASIENTO_FAC_COMPRA_35: 'LIBRO DIARIO'!$A$223
Name ASIENTO_FAC_COMPRA_36: 'LIBRO DIARIO'!$A$231
Name ASIENTO_FAC_COMPRA_37: 'LIBRO DIARIO'!$A$237
Name ASIENTO_FAC_COMPRA_38: 'LIBRO DIARIO'!$A$243
Name ASIENTO_FAC_COMPRA_39: 'LIBRO DIARIO'!$A$251
Name ASIENTO_FAC_COMPRA_4: 'LIBRO DIARIO'!$A$28
Name ASIENTO_FAC_COMPRA_40: 'LIBRO DIARIO'!$A$259
Name ASIENTO_FAC_COMPRA_41: 'LIBRO DIARIO'!$A$267
Name ASIENTO_FAC_COMPRA_42: 'LIBRO DIARIO'!$A$277
Name ASIENTO_FAC_COMPRA_5: 'LIBRO DIARIO'!$A$35
Name ASIENTO_FAC_COMPRA_6: 'LIBRO DIARIO'!$A$44
Name ASIENTO_FAC_COMPRA_7: 'LIBRO DIARIO'!$A$51
Name ASIENTO_FAC_COMPRA_8: 'LIBRO DIARIO'!$A$54
Name ASIENTO_FAC_COMPRA_9: 'LIBRO DIARIO'!$A$59
Name FACTURA_COMPRA___1: COMPRAS!$C$6
Name FACTURA_COMPRA___10: COMPRAS!$C$251
Name FACTURA_COMPRA___11: COMPRAS!$C$274
Name FACTURA_COMPRA___12: COMPRAS!$C$303
Name FACTURA_COMPRA___13: COMPRAS!$C$329
Name FACTURA_COMPRA___14: COMPRAS!$C$357
Name FACTURA_COMPRA___15: COMPRAS!$C$385
Name FACTURA_COMPRA___16: COMPRAS!$C$413
Name FACTURA_COMPRA___17: COMPRAS!$C$441
Name FACTURA_COMPRA___18: COMPRAS!$C$474
Name FACTURA_COMPRA___19: COMPRAS!$C$505
Name FACTURA_COMPRA___2: COMPRAS!$C$34
Name FACTURA_COMPRA___20: COMPRAS!$C$528
Name FACTURA_COMPRA___21: COMPRAS!$C$551
Name FACTURA_COMPRA___22: COMPRAS!$C$574
Name FACTURA_COMPRA___23: COMPRAS!$C$597
Name FACTURA_COMPRA___24: COMPRAS!$C$626
Name FACTURA_COMPRA___25: COMPRAS!$C$652

Sheet PRODUCTOS
A1: PRODUCTO INVENTARIO | C1: IVA
A2: I001 | B2: ACEITE DE VASELINA GL.QF | C2: SI
A3: I002 | B3: Bastidor | C3: SI
A4: I003 | B4: Tira Color Dorado Con Filos Negros De 7.5 Ancho | C4: SI
A5: I004 | B5: Blanca Estucada Semimate | C5: SI
A6: I005 | B6: Chocolate Estucada Semimate | C6: SI
A7: I006 | B7: Azúl Con Dorado | C7: SI
A8: I007 | B8: pino natural procesado con ceja izq | C8: SI
A9: I008 | B9: pino natural peq. Procesado ceja | C9: SI
A10: I009 | B10: pino natural procesado con ceja der | C10: SI
A11: I0010 | B11: Labrada/Verde Con Beige | C11: NO
A12: I0011 | B12: Verde Con Dorado | C12: NO
A13: I0012 | B13: Dorado Con Trenza | C13: NO
... A15: I0014 | B15: Plateada Llana | C15: NO
A18: GASTOS O SERVICIOS
A19: CT-COMPRAS49127 | B19: Arriendo de Local | C19: SI
A20: CT-COMPRAS57289 | B20: ANUNCIO PUBLICITARIO | C20: SI
A21: CT-COMPRAS52464 | B21: RESMAS DE PAPEL BOND | C21: SI | D21: UTILES Y PAPELERIA
A22: CT-COMPRAS4105 | B22: CAJAS DE ESFEROS | C22: SI | D22: UTILES Y PAPELERIA
A23: CT-COMPRAS49110 | B23: AGENDAS | C23: SI | D23: UTILES Y PAPELERIA
A24: CT-COMPRAS13417 | B24: ALMUERZOS | C24: SI
A25: CT-COMPRAS45097 | B25: PORTATIL HP | C25: SI
A26: CT-COMPRAS8826 | B26: PAGO ENERGIA | C26: SI
A27: CT-COMPRAS45439 | B27: MANTENIMIENTO EDIFICIO | C27: SI
B28: PEGANOL | C28: NO | D28: UTILES Y PAPELERIA
B29: ESCARCHA | C29: NO | D29: UTILES Y PAPELERIA
B30: CARTULINA | C30: NO | D30: UTILES Y PAPELERIA
A33: VENTA SERVICIO
A34: SP300 | B34: SERVICIOS PRESTADOS 300 | C34: SI
A35: SP1000 | B35: SERVICIOS PRESTADOS 1000 | C35: SI
A36: SP200 | B36: SERVICIOS PRESTADOS 200 | C36: SI
A37: SP2500 | B37: SERVICIOS PRESTADOS 2500 | C37: SI

Sheet FACTURA COMPRA
A3: DESCRIPCION | C3: DOCUMENTO # | D3: PROVEEDOR | E3: FECHA EMISIÓN | F3: SUBTOTAL | G3: RETENCION | H3: TOTAL
A4: ESTADO | B4: =+COMPRAS!C32 -> Pendiente | C4: =+CONCATENATE(COMPRAS!C6," ",COMPRAS!C26) -> FACTURA COMPRA # 1 001-001-100 | D4: =CONCATENATE(COMPRAS!C8," / ",COMPRAS!C9) -> VICTOR LOPEZ SANDOVAL / 1712458544001 | E4: =+COMPRAS!C27 -> 43497 | F4: =+COMPRAS!E15+COMPRAS!E16-COMPRAS!E17 -> 424.4316 | G4: =+COMPRAS!M24 -> 55.176108 | H4: =+COMPRAS!N24 -> 420.18728
A5: TIPO | B5: =+COMPRAS!C13 -> FACTURA
A6: CREDITO | B6: =+COMPRAS!C31 -> 420.18728
A7: ESTADO | B7: =+COMPRAS!C60 -> Emitido | C7: =+CONCATENATE(COMPRAS!C34," ",COMPRAS!C54) -> FACTURA COMPRA # 2 001-001-101 | D7: =CONCATENATE(COMPRAS!C36," / ",COMPRAS!C37) -> VICTOR LOPEZ SANDOVAL / 1712458544001 | E7: =+COMPRAS!C44 -> 43497 | F7: =+COMPRAS!E43+COMPRAS!E44-COMPRAS!E45 -> 424.4316 | G7: =+COMPRAS!M52 -> 49.234066 | H7: =+COMPRAS!N52 -> 426.12933
A8: TIPO | B8: =+COMPRAS!C41 -> FACTURA
A9: CREDITO | B9: =+IF(COMPRAS!C60="Emitido","No",0) -> No
A10: ESTADO | B10: =+COMPRAS!C88 -> Emitido | C10: =+CONCATENATE(COMPRAS!C62," ",COMPRAS!C82) -> FACTURA COMPRA # 3 001-001-102 | D10: =CONCATENATE(COMPRAS!C64," / ",COMPRAS!C65) -> VICTOR LOPEZ SANDOVAL / 1712458544001 | E10: =+COMPRAS!C72 -> 43497 | F10: =+COMPRAS!E71+COMPRAS!E72-COMPRAS!E73 -> 424.4316 | G10: =+COMPRAS!M80 -> 33.954528 | H10: =+COMPRAS!N80 -> 441.40886
A11: TIPO | B11: =+COMPRAS!C69 -> FACTURA
A12: CREDITO | B12: =+IF(COMPRAS!C88="Emitido","No",0) -> No
A13: ESTADO | B13: =+COMPRAS!C116 -> Emitido | C13: =+CONCATENATE(COMPRAS!C90," ",COMPRAS!C110) -> FACTURA COMPRA # 4 001-001-103 | D13: =CONCATENATE(COMPRAS!C92," / ",COMPRAS!C93) -> ILUMAX / 1708492408001 | E13: =+COMPRAS!C100 -> 43498 | F13: =+COMPRAS!E99+COMPRAS!E100-COMPRAS!E101 -> 1180.8087 | G13: =+COMPRAS!M108 -> 110.99602 | H13: =+COMPRAS!N108 -> 1211.5097
A14: TIPO | B14: =+COMPRAS!C97 -> FACTURA
A15: CREDITO | B15: =+IF(COMPRAS!C116="Emitido","No",0) -> No
A16: ESTADO | B16: =+COMPRAS!C149 -> Emitido | C16: =+CONCATENATE(COMPRAS!C118," ",COMPRAS!C138) -> FACTURA COMPRA # 5 001-001-104 | D16: =CONCATENATE(COMPRAS!C120," / ",COMPRAS!C121) -> ILUMAX / 1708492408001 | E16: =+COMPRAS!C128 -> 43498 | F16: =+COMPRAS!E127+COMPRAS!E128-COMPRAS!E129 -> 1180.8087 | G16: =+COMPRAS!M136 -> 108.6344 | H16: =+COMPRAS!N136 -> 1213.8713
A17: TIPO | B17: =+COMPRAS!C125 -> FACTURA
A18: CREDITO | B18: =+IF(COMPRAS!C149="Emitido","No",0) -> No
A19: ESTADO | B19: =+COMPRAS!C180 -> Pendiente | C19: =+CONCATENATE(COMPRAS!C151," ",COMPRAS!C171) -> FACTURA COMPRA # 6 001-001-105 | D19: =CONCATENATE(COMPRAS!C153," / ",COMPRAS!C154) -> ILUMAX / 1708492408001 | E19: =+COMPRAS!C161 -> 43498 | F19: =+COMPRAS!E160+COMPRAS!E161-COMPRAS!E162 -> 1180.8087 | G19: =+COMPRAS!M169 -> 51.955583 | H19: =+COMPRAS!N169 -> 1270.5502
A20: TIPO | B20: =+COMPRAS!C158 -> FACTURA
A21: CREDITO | B21: =+COMPRAS!C179 -> 508.22006
A22: ESTADO | B22: =+COMPRAS!C203 -> Pendiente | C22: =+CONCATENATE(COMPRAS!C182," ",COMPRAS!C193,"-",COMPRAS!C194,"-",COMPRAS!C195) -> FACTURA COMPRA # 7 001-001-106 | D22: =CONCATENATE(COMPRAS!C184," / ",COMPRAS!C185) -> VICTOR LOPEZ SANDOVAL / 1712458544001 | E22: =+COMPRAS!C192 -> 43497 | F22: =+COMPRAS!E191+COMPRAS!E192-COMPRAS!E193 -> 424.4316 | G22: =+COMPRAS!M142 -> 0 | H22: =+COMPRAS!E195 -> 475.36339
A23: TIPO | B23: =+COMPRAS!C189 -> FACTURA
A24: CREDITO | B24: =+COMPRAS!C202 -> 475.36339
A25: ESTADO | B25: =+COMPRAS!C226 -> Emitido | C25: =+CONCATENATE(COMPRAS!C205," ",COMPRAS!C216,"-",COMPRAS!C217,"-",COMPRAS!C218) -> FACTURA COMPRA # 8 001-001-107 | D25: =CONCATENATE(COMPRAS!C207," / ",COMPRAS!C208) -> VICTOR LOPEZ SANDOVAL / 1712458544001 | E25: =+COMPRAS!C215 -> 43497 | F25: =+COMPRAS!E214+COMPRAS!E215-COMPRAS!E216 -> 501.8516 | G25: =+COMPRAS!M175 -> 0 | H25: =+COMPRAS!E218 -> 562.07379
A26: TIPO | B26: =+COMPRAS!C212 -> FACTURA
A27: CREDITO | B27: =+IF(COMPRAS!C226="Emitido","No",0) -> No
A28: ESTADO | B28: =+COMPRAS!C249 -> Emitido | C28: =+CONCATENATE(COMPRAS!C228," ",COMPRAS!C239,"-",COMPRAS!C240,"-",COMPRAS!C241) -> FACTURA COMPRA # 9 001-001-108 | D28: =CONCATENATE(COMPRAS!C230," / ",COMPRAS!C231) -> VICTOR LOPEZ SANDOVAL / 1712458544001 | E28: =+COMPRAS!C238 -> 43497 | F28: =+COMPRAS!E237+COMPRAS!E238-COMPRAS!E239 -> 405.8116 | G28: =+COMPRAS!M148 -> 0 | H28: =+COMPRAS!E241 -> 454.50899
A29: TIPO | B29: =+COMPRAS!C235 -> FACTURA
A30: CREDITO | B30: =+IF(COMPRAS!C249="Emitido","No",0) -> No
A31: ESTADO | B31: =+COMPRAS!C272 -> Emitido | C31: =+CONCATENATE(COMPRAS!C251," ",COMPRAS!C262,"-",COMPRAS!C263,"-",COMPRAS!C264) -> FACTURA COMPRA # 10 001-001-109 | D31: =CONCATENATE(COMPRAS!C253," / ",COMPRAS!C254) -> ILUMAX / 1708492408001 | E31: =+COMPRAS!C261 -> 43498 | F31: =+COMPRAS!E260+COMPRAS!E261-COMPRAS!E262 -> 1180.8087 | G31: =+COMPRAS!M181 -> 0 | H31: =+COMPRAS!E264 -> 1322.5057
A32: TIPO | B32: =+COMPRAS!C258 -> FACTURA
A33: CREDITO | B33: =+IF(COMPRAS!C272="Emitido","No",0) -> No
A34: ESTADO | B34: =+COMPRAS!C301 -> Emitido | C34: =+CONCATENATE(COMPRAS!C274," ",COMPRAS!C285,"-",COMPRAS!C286,"-",COMPRAS!C287) -> FACTURA COMPRA # 11 001-001-110 | D34: =CONCATENATE(COMPRAS!C276," / ",COMPRAS!C277) -> ILUMAX / 1708492408001 | E34: =+COMPRAS!C284 -> 43498 | F34: =+COMPRAS!E283+COMPRAS!E284-COMPRAS!E285 -> 1180.8087 | G34: =+COMPRAS!M154 -> 0 | H34: =+COMPRAS!E287 -> 1322.5057
A35: TIPO | B35: =+COMPRAS!C281 -> FACTURA
A36: CREDITO | B36: =+IF(COMPRAS!C301="Emitido","No",0) -> No
A37: ESTADO | B37: =+COMPRAS!C317 -> Pendiente | C37: =+CONCATENATE(COMPRAS!C303," ",COMPRAS!C314,"-",COMPRAS!C315,"-",COMPRAS!C316) -> FACTURA COMPRA # 12 001-001-111 | D37: =CONCATENATE(COMPRAS!C305," / ",COMPRAS!C306) -> ILUMAX / 1708492408001 | E37: =+COMPRAS!C313 -> 43498 | F37: =+COMPRAS!E312+COMPRAS!E313-COMPRAS!E314 -> 1180.8087 | G37: =+COMPRAS!M187 -> 0 | H37: =+COMPRAS!E316 -> 1322.5057
A38: TIPO | B38: =+COMPRAS!C310 -> FACTURA
A39: CREDITO | B39: =+COMPRAS!C326 -> 529.0023

Sheet COMPRAS
A1: Nro Comprobante de autorizacion de retenciones
A2: G-EMPRESA-DOCUMENTOS AUTORIZADOS SRI
A3: COMPROBANTE DE RENTECION | D3: 999999999
A6: I-SD-R | B6: Deuda | C6: FACTURA COMPRA # 1
B7: FACTURA COMPRA
B8: Proveedor | C8: VICTOR LOPEZ SANDOVAL | D8: CANT | E8: CODIGO | F8: IVA | G8: PRODUCTO/DESCRIP | H8: P. UNI | I8: SUBT 0% | J8: SUBT 12% | K8: DESC % | L8: DESC $ | M8: DESC TOTAL | N8: IVA | O8: TOTAL | P8: CONTABILIDAD | Q8: NRO CUENTA | R8: TIPO
B9: idProv | C9: 1712458544001 | D9: 61 | E9: 396-12 | F9: 0.12 | G9: ACEITE DE VASELINA GL.QF | H9: 1.45 | I9: =+IF(F9=0%,D9*H9,0) -> 0 | J9: =+IF(F9=12%,D9*H9,0) -> 88.45 | K9: 0 | L9: 0 | M9: =+J9*K9 -> 0 | N9: =+(J9-M9)*F9 -> 10.614 | O9: =+J9-M9+N9 -> 99.064 | P9: INVENTARIO | Q9: 1.1.02.04.001 | R9: INVENTARIO
B10: tpIdProv | C10: 01 | D10: 56.21 | E10: 396-2507 | F10: 0.12 | G10: Bastidor | H10: 2.96 | I10: =+IF(F10=0%,D10*H10,0) -> 0 | J10: =+IF(F10=12%,D10*H10,0) -> 166.3816 | K10: 0 | L10: 0 | M10: =+J10*K10 -> 0 | N10: =+(J10-M10)*F10 -> 19.965792 | O10: =+J10-M10+N10 -> 186.34739 | P10: INVENTARIO | Q10: 1.1.02.04.001 | R10: INVENTARIO
B11: Sustento T | C11: INVENTARIO CREDITO TRIBUTARIO PARA DECLARACION DE IVA | D11: 49 | E11: 396-306 | F11: 0.12 | G11: Tira Color Dorado Con Filos Negros De 7.5 Ancho | H11: 3.15 | I11: =+IF(F11=0%,D11*H11,0) -> 0 | J11: =+IF(F11=12%,D11*H11,0) -> 154.35 | K11: 0 | L11: 0 | M11: =+J11*K11 -> 0 | N11: =+(J11-M11)*F11 -> 18.522 | O11: =+J11-M11+N11 -> 172.872 | P11: INVENTARIO | Q11: 1.1.02.04.001 | R11: INVENTARIO
B12: codSustento | C12: 06 | D12: 12.2 | E12: 362-2889 | F12: 0.12 | G12: Blanca Estucada Semimate | H12: 1.25 | I12: =+IF(F12=0%,D12*H12,0) -> 0 | J12: =+IF(F12=12%,D12*H12,0) -> 15.25 | K12: 0 | L12: 0 | M12: =+J12*K12 -> 0 | N12: =+(J12-M12)*F12 -> 1.83 | O12: =+J12-M12+N12 -> 17.08 | P12: INVENTARIO | Q12: 1.1.02.04.001 | R12: INVENTARIO
B13: Tipo Comp Aut | C13: FACTURA
B14: tipoComprobante | C14: 1
B15: autorizacion | C15: 1120335551 | D15: SUBT 0% | E15: =+SUM(I9:I12) -> 0
B16: Fecha Emi | C16: 43497 | D16: SUBTOTAL 12% | E16: =+SUM(J9:J14) -> 424.4316
B17: Establecimiento | C17: 001 | D17: DESCUENTO | E17: =SUM(M9:M14) -> 0 | G17: INGRESE MAL EL SUSTENTO
B18: Punto Emision | C18: 001 | D18: IVA | E18: =SUM(N9:N14) -> 50.931792
B19: Secuencial | C19: 100 | D19: TOTAL | E19: =SUM(O9:O14) -> 475.36339
B22: RETENCION FACTURA COMPRA
B23: Establecimiento Ret1 | C23: 001 | D23: CONTABILIDAD | E23: CUENTA CONT. | G23: BASE IMPONIBLE | H23: IMPUESTO | J23: PORCENTAJE RETENCION | L23: VALOR RET. | M23: TOTAL RET | N23: TOTAL FACT - RET
B24: Pto Emision Ret1 | C24: 001 | D24: 2.1.01.07.006 | E24: Retencion IVA por pagar 100% | G24: 731 | H24: IVA | J24: 1 | L24: =+E18*J24 -> 50.931792 | M24: =+L24+L25 -> 55.176108 | N24: =+E19-M24 -> 420.18728
B25: Secuencial Ret 1 | C25: 501 | D25: 2.1.01.06.001 | E25: Impuesto a la renta por pagar 1% | G25: 309 | H25: RENTA | J25: 0.01 | L25: =(E16+E15-E17)*J25 -> 4.244316
B26: Nro Factura | C26: =+CONCATENATE(C17,"-",C18,"-",C19) -> 001-001-100
B27: Fecha | C27: =+C16 -> 43497
B28: Tipo de Desgloce | C28: Normal | E28: ASIENTO DIARIO
B29: Boton | C29: Pendiente | E29: KARDEX
B30: Cuenta Contable | C30: Proveedores
B31: Valor a pagar | C31: =+E19-M24 -> 420.18728
B32: Estado | C32: Pendiente
A34: I-SD-R | B34: Efectivo | C34: FACTURA COMPRA # 2
B35: FACTURA COMPRA
B36: Proveedor | C36: VICTOR LOPEZ SANDOVAL | D36: CANT | E36: CODIGO | F36: IVA | G36: PRODUCTO/DESCRIP | H36: P. UNI | I36: SUBT 0% | J36: SUBT 12% | K36: DESC % | L36: DESC $ | M36: DESC TOTAL | N36: IVA | O36: TOTAL | P36: CONTABILIDAD | Q36: NRO CUENTA | R36: TIPO
B37: idProv | C37: 1712458544001 | D37: 61 | E37: 396-12 | F37: 0.12 | G37: ACEITE DE VASELINA GL.QF | H37: 1.45 | I37: =+IF(F37=0%,D37*H37,0) -> 0 | J37: =+IF(F37=12%,D37*H37,0) -> 88.45 | K37: 0 | L37: 0 | M37: =+J37*K37 -> 0 | N37: =+(J37-M37)*F37 -> 10.614 | O37: =+J37-M37+N37 -> 99.064 | P37: INVENTARIO | Q37: 1.1.02.04.001 | R37: INVENTARIO
B38: tpIdProv | C38: 01 | D38: 56.21 | E38: 396-2507 | F38: 0.12 | G38: Bastidor | H38: 2.96 | I38: =+IF(F38=0%,D38*H38,0) -> 0 | J38: =+IF(F38=12%,D38*H38,0) -> 166.3816 | K38: 0 | L38: 0 | M38: =+J38*K38 -> 0 | N38: =+(J38-M38)*F38 -> 19.965792 | O38: =+J38-M38+N38 -> 186.34739 | P38: INVENTARIO | Q38: 1.1.02.04.001 | R38: INVENTARIO
B39: Sustento T | C39: INVENTARIO CREDITO TRIBUTARIO PARA DECLARACION DE IVA | D39: 49 | E39: 396-306 | F39: 0.12 | G39: Tira Color Dorado Con Filos Negros De 7.5 Ancho | H39: 3.15 | I39: =+IF(F39=0%,D39*H39,0) -> 0 | J39: =+IF(F39=12%,D39*H39,0) -> 154.35 | K39: 0 | L39: 0 | M39: =+J39*K39 -> 0 | N39: =+(J39-M39)*F39 -> 18.522 | O39: =+J39-M39+N39 -> 172.872 | P39: INVENTARIO | Q39: 1.1.02.04.001 | R39: INVENTARIO
B40: codSustento | C40: 06 | D40: 12.2 | E40: 362-2889 | F40: 0.12 | G40: Blanca Estucada Semimate | H40: 1.25 | I40: =+IF(F40=0%,D40*H40,0) -> 0 | J40: =+IF(F40=12%,D40*H40,0) -> 15.25 | K40: 0 | L40: 0 | M40: =+J40*K40 -> 0 | N40: =+(J40-M40)*F40 -> 1.83 | O40: =+J40-M40+N40 -> 17.08 | P40: INVENTARIO | Q40: 1.1.02.04.001 | R40: INVENTARIO
B41: Tipo Comp Aut | C41: FACTURA
B42: tipoComprobante | C42: 1
B43: autorizacion | C43: 1120335551 | D43: SUBTOTAL 0% | E43: =+SUM(I37:I40) -> 0
B44: Fecha Emi | C44: 43497 | D44: SUBTOTAL 12% | E44: =+SUM(J37:J42) -> 424.4316
B45: Establecimiento | C45: 001 | D45: DESCUENTO | E45: =SUM(M37:M42) -> 0
B46: Punto Emision | C46: 001 | D46: IVA | E46: =SUM(N37:N42) -> 50.931792
B47: Secuencial | C47: 101 | D47: TOTAL | E47: =SUM(O37:O42) -> 475.36339
B50: RETENCION FACTURA COMPRA
B51: Establecimiento Ret1 | C51: 001 | D51: CONTABILIDAD | E51: CUENTA CONT. | G51: BASE IMPONIBLE | H51: IMPUESTO | J51: PORCENTAJE RETENCION | L51: VALOR RET. | M51: TOTAL RET | N51: TOTAL FACT - RET
B52: Pto Emision Ret1 | C52: 001 | D52: 2.1.01.07.003 | E52: Retencion IVA por pagar 30% | G52: 725 | H52: IVA | J52: 0.3 | L52: =+E46*J52 -> 15.279538 | M52: =+L52+L53 -> 49.234066 | N52: =+E47-M52 -> 426.12933
B53: Secuencial Ret 1 | C53: 502 | D53: 2.1.01.06.003 | E53: Impuesto a la renta por pagar 8% | G53: 320 | H53: RENTA | J53: 0.08 | L53: =(E44+E43-E45)*J53 -> 33.954528
B54: Nro Factura | C54: =+CONCATENATE(C45,"-",C46,"-",C47) -> 001-001-101
B55: Fecha | C55: =+C44 -> 43497
B56: Tipo de Desgloce | C56: Normal | E56: ASIENTO DIARIO
B57: Boton | C57: Pagar | E57: KARDEX
B58: Cuenta Contable | C58: Caja General
B59: Valor a pagar | C59: =+E47-M52 -> 426.12933
B60: Estado | C60: Emitido
A62: I-SD-R | B62: T. C. | C62: FACTURA COMPRA # 3
B63: FACTURA COMPRA
B64: Proveedor | C64: VICTOR LOPEZ SANDOVAL | D64: CANT | E64: CODIGO | F64: IVA | G64: PRODUCTO/DESCRIP | H64: P. UNI | I64: SUBT 0% | J64: SUBT 12% | K64: DESC % | L64: DESC $ | M64: DESC TOTAL | N64: IVA | O64: TOTAL | P64: CONTABILIDAD | Q64: NRO CUENTA | R64: TIPO
B65: idProv | C65: 1712458544001 | D65: 61 | E65: 396-12 | F65: 0.12 | G65: ACEITE DE VASELINA GL.QF | H65: 1.45 | I65: =+IF(F65=0%,D65*H65,0) -> 0 | J65: =+IF(F65=12%,D65*H65,0) -> 88.45 | K65: 0 | L65: 0 | M65: =+J65*K65 -> 0 | N65: =+(J65-M65)*F65 -> 10.614 | O65: =+J65-M65+N65 -> 99.064 | P65: INVENTARIO | Q65: 1.1.02.04.001 | R65: INVENTARIO
B66: tpIdProv | C66: 01 | D66: 56.21 | E66: 396-2507 | F66: 0.12 | G66: Bastidor | H66: 2.96 | I66: =+IF(F66=0%,D66*H66,0) -> 0 | J66: =+IF(F66=12%,D66*H66,0) -> 166.3816 | K66: 0 | L66: 0 | M66: =+J66*K66 -> 0 | N66: =+(J66-M66)*F66 -> 19.965792 | O66: =+J66-M66+N66 -> 186.34739 | P66: INVENTARIO | Q66: 1.1.02.04.001 | R66: INVENTARIO
B67: Sustento T | C67: INVENTARIO CREDITO TRIBUTARIO PARA DECLARACION DE IVA | D67: 49 | E67: 396-306 | F67: 0.12 | G67: Tira Color Dorado Con Filos Negros De 7.5 Ancho | H67: 3.15 | I67: =+IF(F67=0%,D67*H67,0) -> 0 | J67: =+IF(F67=12%,D67*H67,0) -> 154.35 | K67: 0 | L67: 0 | M67: =+J67*K67 -> 0 | N67: =+(J67-M67)*F67 -> 18.522 | O67: =+J67-M67+N67 -> 172.872 | P67: INVENTARIO | Q67: 1.1.02.04.001 | R67: INVENTARIO
B68: codSustento | C68: 06 | D68: 12.2 | E68: 362-2889 | F68: 0.12 | G68: Blanca Estucada Semimate | H68: 1.25 | I68: =+IF(F68=0%,D68*H68,0) -> 0 | J68: =+IF(F68=12%,D68*H68,0) -> 15.25 | K68: 0 | L68: 0 | M68: =+J68*K68 -> 0 | N68: =+(J68-M68)*F68 -> 1.83 | O68: =+J68-M68+N68 -> 17.08 | P68: INVENTARIO | Q68: 1.1.02.04.001 | R68: INVENTARIO
B69: Tipo Comp Aut | C69: FACTURA
B70: tipoComprobante | C70: 1
B71: autorizacion | C71: 1120335551 | D71: SUBTOTAL 0% | E71: =+SUM(I65:I68) -> 0
B72: Fecha Emi | C72: 43497 | D72: SUBTOTAL 12% | E72: =+SUM(J65:J70) -> 424.4316
B73: Establecimiento | C73: 001 | D73: DESCUENTO | E73: =SUM(M65:M70) -> 0
B74: Punto Emision | C74: 001 | D74: IVA | E74: =SUM(N65:N70) -> 50.931792
B75: Secuencial | C75: 102 | D75: TOTAL | E75: =SUM(O65:O70) -> 475.36339
B78: RETENCION FACTURA COMPRA
B79: Establecimiento Ret1 | C79: 001 | D79: CONTABILIDAD | E79: CUENTA CONT. | G79: BASE IMPONIBLE | H79: IMPUESTO | J79: PORCENTAJE RETENCION | L79: VALOR RET. | M79: TOTAL RET | N79: TOTAL FACT - RET
B80: Pto Emision Ret1 | C80: 001 | D80: 2.1.01.07.004 | E80: Retencion IVA por pagar 50% | G80: 727 | H80: IVA | J80: 0.5 | L80: =+E74*J80 -> 25.465896 | M80: =+L80+L81 -> 33.954528 | N80: =+E75-M80 -> 441.40886
B81: Secuencial Ret 1 | C81: 503 | D81: 2.1.01.06.002 | E81: Impuesto a la renta por pagar 2% | G81: 344 | H81: RENTA | J81: 0.02 | L81: =(E72+E71-E73)*J81 -> 8.488632
B82: Nro Factura | C82: =+CONCATENATE(C73,"-",C74,"-",C75) -> 001-001-102
B83: Fecha | C83: =+C72 -> 43497
B84: Tipo de Desgloce | C84: Normal | E84: ASIENTO DIARIO
B85: Boton | C85: Tarjeta de Credito | E85: KARDEX
B86: Cuenta Contable | C86: Sociedades Financieras
B87: Valor a pagar | C87: =+E75-M80 -> 441.40886
B88: Estado | C88: Emitido
A90: I-SD-R | B90: MX 1 OP | C90: FACTURA COMPRA # 4
B91: FACTURA COMPRA
B92: Proveedor | C92: ILUMAX | D92: CANT | E92: CODIGO | F92: IVA | G92: PRODUCTO/DESCRIP | H92: P. UNI | I92: SUBT 0% | J92: SUBT 12% | K92: DESC % | L92: DESC $ | M92: DESC TOTAL | N92: IVA | O92: TOTAL | P92: CONTABILIDAD | Q92: NRO CUENTA | R92: TIPO
B93: idProv | C93: 1708492408001 | D93: 118.47 | E93: I006 | F93: 0.12 | G93: Azúl Con Dorado | H93: 1.47 | I93: =+IF(F93=0%,D93*H93,0) -> 0 | J93: =+IF(F93=12%,D93*H93,0) -> 174.1509 | K93: 0 | L93: 0 | M93: =+J93*K93 -> 0 | N93: =+(J93-M93)*F93 -> 20.898108 | O93: =+J93-M93+N93 -> 195.04901 | P93: INVENTARIO | Q93: 1.1.02.04.001 | R93: INVENTARIO
B94: tpIdProv | C94: 01 | D94: 249.58 | E94: I007 | F94: 0.12 | G94: pino natural procesado con ceja izq | H94: 2.96 | I94: =+IF(F94=0%,D94*H94,0) -> 0 | J94: =+IF(F94=12%,D94*H94,0) -> 738.7568 | K94: 0 | L94: 0 | M94: =+J94*K94 -> 0 | N94: =+(J94-M94)*F94 -> 88.650816 | O94: =+J94-M94+N94 -> 827.40762 | P94: INVENTARIO | Q94: 1.1.02.04.001 | R94: INVENTARIO
B95: Sustento T | C95: INVENTARIO CREDITO TRIBUTARIO PARA DECLARACION DE IVA | D95: 73.54 | E95: I008 | F95: 0.12 | G95: pino natural peq. Procesado ceja | H95: 3.15 | I95: =+IF(F95=0%,D95*H95,0) -> 0 | J95: =+IF(F95=12%,D95*H95,0) -> 231.651 | K95: 0 | L95: 0 | M95: =+J95*K95 -> 0 | N95: =+(J95-M95)*F95 -> 27.79812 | O95: =+J95-M95+N95 -> 259.44912 | P95: INVENTARIO | Q95: 1.1.02.04.001 | R95: INVENTARIO
B96: codSustento | C96: 06 | D96: 29 | E96: I009 | F96: 0.12 | G96: pino natural procesado con ceja der | H96: 1.25 | I96: =+IF(F96=0%,D96*H96,0) -> 0 | J96: =+IF(F96=12%,D96*H96,0) -> 36.25 | K96: 0 | L96: 0 | M96: =+J96*K96 -> 0 | N96: =+(J96-M96)*F96 -> 4.35 | O96: =+J96-M96+N96 -> 40.6 | P96: INVENTARIO | Q96: 1.1.02.04.001 | R96: INVENTARIO
B97: Tipo Comp Aut | C97: FACTURA
B98: tipoComprobante | C98: 1
B99: autorizacion | C99: 1122728319 | D99: SUBTOTAL 0% | E99: =+SUM(I93:I96) -> 0
B100: Fecha Emi | C100: 43498 | D100: SUBTOTAL 12% | E100: =+SUM(J93:J98) -> 1180.8087
B101: Establecimiento | C101: 001 | D101: DESCUENTO | E101: =SUM(M93:M98) -> 0
B102: Punto Emision | C102: 001 | D102: IVA | E102: =SUM(N93:N98) -> 141.69704
B103: Secuencial | C103: 103 | D103: TOTAL | E103: =SUM(O93:O98) -> 1322.5057
B106: RETENCION FACTURA COMPRA
B107: Establecimiento Ret1 | C107: 001 | D107: CONTABILIDAD | E107: CUENTA CONT. | G107: BASE IMPONIBLE | H107: IMPUESTO | J107: PORCENTAJE RETENCION | L107: VALOR RET. | M107: TOTAL RET | N107: TOTAL FACT - RET
B108: Pto Emision Ret1 | C108: 001 | D108: 2.1.01.07.005 | E108: Retencion IVA por pagar 70% | G108: 729 | H108: IVA | J108: 0.7 | L108: =+E102*J108 -> 99.187931 | M108: =+L108+L109 -> 110.99602 | N108: =+E103-M108 -> 1211.5097
B109: Secuencial Ret 1 | C109: 504 | D109: 2.1.01.06.001 | E109: Impuesto a la renta por pagar 1% | G109: 312 | H109: RENTA | J109: 0.01 | L109: =(E100+E99-E101)*J109 -> 11.808087
B110: Nro Factura | C110: =+CONCATENATE(C101,"-",C102,"-",C103) -> 001-001-103
B111: Fecha | C111: =+C102 -> 001
B112: Tipo de Desgloce | C112: Mixto | E112: ASIENTO DIARIO
B113: Tipo de Pago | C113: Con utilización del sistema financiero | E113: KARDEX
...

Sheet VENTAS
A1: Nro Comprobante de autorizacion de Facturas
A2: G-EMPRESA-DOCUMENTOS AUTORIZADOS SRI
A3: Facturación | D3: 123456789
A6: I-SD-R | B6: Deuda | C6: FACTURA VENTA # 1
B7: FACTURA VENTA
B8: Cliente | C8: LEONEL LEMA | D8: CANT | E8: CODIGO | F8: IVA | G8: PRODUCTO/DESCRIP | H8: P. UNI | I8: SUBT 0% | J8: SUBT 12% | K8: DESC % | L8: DESC $ | M8: DESC TOTAL | N8: IVA | O8: TOTAL | P8: CONTABILIDAD | Q8: NRO CUENTA | R8: TIPO | S8: KARDEX P | T8: KARDEX T
B9: idCliente | C9: 1720696275 | D9: 15 | E9: 396-12 | F9: 0.12 | G9: ACEITE DE VASELINA GL.QF | H9: 1.96 | I9: =+IF(F9=0%,D9*H9,0) -> 0 | J9: =+IF(F9=12%,D9*H9,0) -> 29.4 | K9: 0 | L9: 0 | M9: =+J9*K9 -> 0 | N9: =+(J9-M9)*F9 -> 3.528 | O9: =+J9-M9+N9 -> 32.928 | P9: INVENTARIO | Q9: 1.1.02.04.001 | R9: INVENTARIO | S9: =+KARDEX!K83 -> 1.4566071 | T9: =+S9*D9 -> 21.849107
B10: tpIdCliente | C10: 05 | D10: 12.37 | E10: 396-2507 | F10: 0.12 | G10: Bastidor | H10: 4 | I10: =+IF(F10=0%,D10*H10,0) -> 0 | J10: =+IF(F10=12%,D10*H10,0) -> 49.48 | K10: 0 | L10: 0 | M10: =+J10*K10 -> 0 | N10: =+(J10-M10)*F10 -> 5.9376 | O10: =+J10-M10+N10 -> 55.4176 | P10: INVENTARIO | Q10: 1.1.02.04.001 | R10: INVENTARIO | S10: =+KARDEX!K84 -> 2.880272 | T10: =+S10*D10 -> 35.628965
B11: Tipo de Comprobante | C11: Documentos autorizados utilizados en ventas excepto N/C N/D | D11: 22.46 | E11: 396-306 | F11: 0.12 | G11: Tira Color Dorado Con Filos Negros De 7.5 Ancho | H11: 4.39 | I11: =+IF(F11=0%,D11*H11,0) -> 0 | J11: =+IF(F11=12%,D11*H11,0) -> 98.5994 | K11: 0 | L11: 0 | M11: =+J11*K11 -> 0 | N11: =+(J11-M11)*F11 -> 11.831928 | O11: =+J11-M11+N11 -> 110.43133 | P11: INVENTARIO | Q11: 1.1.02.04.001 | R11: INVENTARIO | S11: =+KARDEX!K85 -> 3.2521586 | T11: =+S11*D11 -> 73.043482
B12: tipoComprobante | C12: 18 | D12: 8.67 | E12: 362-2889 | F12: 0.12 | G12: Blanca Estucada Semimate | H12: 1.69 | I12: =+IF(F12=0%,D12*H12,0) -> 0 | J12: =+IF(F12=12%,D12*H12,0) -> 14.6523 | K12: 0 | L12: 0 | M12: =+J12*K12 -> 0 | N12: =+(J12-M12)*F12 -> 1.758276 | O12: =+J12-M12+N12 -> 16.410576 | P12: INVENTARIO | Q12: 1.1.02.04.001 | R12: INVENTARIO | S12: =+KARDEX!K86 -> 1.25 | T12: =+S12*D12 -> 10.8375
B13: Tipo de Emisión | C13: Factura Fisica
B14: tipoEm | C14: f | T14: =SUM(T9:T13) -> 141.35905
B15: Fecha Emi | C15: 43513 | D15: SUBT 0% | E15: =+SUM(I9:I12) -> 0
B16: Establecimiento | C16: 001 | D16: SUBTOTAL 12% | E16: =+SUM(J9:J14) -> 192.1317
B17: Punto Emision | C17: 001 | D17: DESCUENTO | E17: =SUM(M9:M14) -> 0
B18: Secuencial | C18: 100 | D18: IVA | E18: =SUM(N9:N14) -> 23.055804
D19: TOTAL | E19: =SUM(O9:O14) -> 215.1875
B22: RETENCION FACTURA VENTA
B23: Establecimiento Ret1 | C23: 001 | D23: CONTABILIDAD | E23: CUENTA CONT. | G23: BASE IMPONIBLE | H23: IMPUESTO | J23: PORCENTAJE RETENCION | L23: VALOR RET. | M23: TOTAL RET | N23: TOTAL FACT - RET
B24: Pto Emision Ret1 | C24: 001 | D24: 2.1.01.07.006 | E24: Retención IVA 100% | G24: 731 | H24: IVA | J24: 1 | L24: =+E18*J24 -> 23.055804 | M24: =+L24+L25 -> 24.977121 | N24: =+E19-M24 -> 190.21038
B25: Secuencial Ret 1 | C25: 501 | D25: 2.1.01.06.001 | E25: Retención en la fuente 1% | G25: 309 | H25: RENTA | J25: 0.01 | L25: =(E16+E15-E17)*J25 -> 1.921317
B26: Autorizacion | C26: 1123134181
B27: Nro Factura | C27: =+CONCATENATE(C16,"-",C17,"-",C18) -> 001-001-100
B28: Fecha | C28: =+C15 -> 43513 | E28: ASIENTO DIARIO | G28: meti mal la retencion compra
B29: Tipo de Desgloce | C29: Normal | E29: KARDEX | G29: era retencion fuente
B30: Boton | C30: Pendiente
B31: Cuenta Contable | C31: Clientes
B32: Valor a pagar | C32: =+E19-M24 -> 190.21038 | G32: aquí no cuadra el valor pendiente
B33: Estado | C33: Pendiente
A35: I-SD-R | B35: Efectivo | C35: FACTURA VENTA # 2
B36: FACTURA VENTA
B37: Cliente | C37: LEONEL LEMA | D37: CANT | E37: CODIGO | F37: IVA | G37: PRODUCTO/DESCRIP | H37: P. UNI | I37: SUBT 0% | J37: SUBT 12% | K37: DESC % | L37: DESC $ | M37: DESC TOTAL | N37: IVA | O37: TOTAL | P37: CONTABILIDAD | Q37: NRO CUENTA | R37: TIPO | S37: KARDEX P | T37: KARDEX T
B38: idCliente | C38: 1720696275 | D38: 12 | E38: 396-12 | F38: 0.12 | G38: ACEITE DE VASELINA GL.QF | H38: 1.96 | I38: =+IF(F38=0%,D38*H38,0) -> 0 | J38: =+IF(F38=12%,D38*H38,0) -> 23.52 | K38: 0 | L38: 0 | M38: =+J38*K38 -> 0 | N38: =+(J38-M38)*F38 -> 2.8224 | O38: =+J38-M38+N38 -> 26.3424 | P38: INVENTARIO | Q38: 1.1.02.04.001 | R38: INVENTARIO | S38: 1.45 | T38: 21.75
B39: tpIdCliente | C39: 05 | D39: 24 | E39: 396-2507 | F39: 0.12 | G39: Bastidor | H39: 4 | I39: =+IF(F39=0%,D39*H39,0) -> 0 | J39: =+IF(F39=12%,D39*H39,0) -> 96 | K39: 0 | L39: 0 | M39: =+J39*K39 -> 0 | N39: =+(J39-M39)*F39 -> 11.52 | O39: =+J39-M39+N39 -> 107.52 | P39: INVENTARIO | Q39: 1.1.02.04.001 | R39: INVENTARIO | S39: 2.96 | T39: 36.6152
B40: Tipo de Comprobante | C40: Documentos autorizados utilizados en ventas excepto N/C N/D | D40: 2.56 | E40: 396-306 | F40: 0.12 | G40: Tira Color Dorado Con Filos Negros De 7.5 Ancho | H40: 4.39 | I40: =+IF(F40=0%,D40*H40,0) -> 0 | J40: =+IF(F40=12%,D40*H40,0) -> 11.2384 | K40: 0 | L40: 0 | M40: =+J40*K40 -> 0 | N40: =+(J40-M40)*F40 -> 1.348608 | O40: =+J40-M40+N40 -> 12.587008 | P40: INVENTARIO | Q40: 1.1.02.04.001 | R40: INVENTARIO | S40: 3.25 | T40: 72.995
B41: tipoComprobante | C41: 18 | D41: 3.65 | E41: 362-2889 | F41: 0.12 | G41: Blanca Estucada Semimate | H41: 1.69 | I41: =+IF(F41=0%,D41*H41,0) -> 0 | J41: =+IF(F41=12%,D41*H41,0) -> 6.1685 | K41: 0 | L41: 0 | M41: =+J41*K41 -> 0 | N41: =+(J41-M41)*F41 -> 0.74022 | O41: =+J41-M41+N41 -> 6.90872 | P41: INVENTARIO | Q41: 1.1.02.04.001 | R41: INVENTARIO | S41: 1.25 | T41: 10.8375
B42: Tipo de Emisión | C42: Factura Fisica
B43: tipoEm | C43: f | T43: 142.1977
B44: Fecha Emi | C44: 43513 | D44: SUBTOTAL 0% | E44: =+SUM(I38:I41) -> 0
B45: Establecimiento | C45: 001 | D45: SUBTOTAL 12% | E45: =+SUM(J38:J43) -> 136.9269
B46: Punto Emision | C46: 001 | D46: DESCUENTO | E46: =SUM(M38:M43) -> 0
B47: Secuencial | C47: 101 | D47: IVA | E47: =SUM(N38:N43) -> 16.431228
D48: TOTAL | E48: =SUM(O38:O43) -> 153.35813
B51: RETENCION FACTURA VENTA
B52: Establecimiento Ret1 | C52: 001 | D52: CONTABILIDAD | E52: CUENTA CONT. | G52: BASE IMPONIBLE | H52: IMPUESTO | J52: PORCENTAJE RETENCION | L52: VALOR RET. | M52: TOTAL RET | N52: TOTAL FACT - RET
B53: Pto Emision Ret1 | C53: 001 | D53: 2.1.01.07.003 | E53: Retencion IVA 30% | G53: 725 | H53: IVA | J53: 0.3 | L53: =+E47*J53 -> 4.9293684 | M53: =+L53+L54 -> 15.88352 | N53: =+E48-M53 -> 137.47461
B54: Secuencial Ret 1 | C54: 502 | D54: 2.1.01.06.003 | E54: Retención en la fuente 8% | G54: 320 | H54: RENTA | J54: 0.08 | L54: =(E45+E44-E46)*J54 -> 10.954152
B55: Autorizacion | C55: 1123134181
B56: Nro Factura | C56: =+CONCATENATE(C45,"-",C46,"-",C47) -> 001-001-101
B57: Fecha | C57: =+C44 -> 43513 | E57: ASIENTO DIARIO
B58: Tipo de Desgloce | C58: Normal | E58: KARDEX
B59: Boton | C59: Pagar
B60: Cuenta Contable | C60: Caja General
B61: Valor a pagar | C61: =+E48-M53 -> 137.47461
B62: Estado | C62: Emitido
A64: I-SD-R | B64: T. C. | C64: FACTURA VENTA # 3
B65: FACTURA VENTA
B66: Cliente | C66: LEONEL LEMA | D66: CANT | E66: CODIGO | F66: IVA | G66: PRODUCTO/DESCRIP | H66: P. UNI | I66: SUBT 0% | J66: SUBT 12% | K66: DESC % | L66: DESC $ | M66: DESC TOTAL | N66: IVA | O66: TOTAL | P66: CONTABILIDAD | Q66: NRO CUENTA | R66: TIPO | S66: KARDEX P | T66: KARDEX T
B67: idCliente | C67: 1720696275 | D67: 60 | E67: 396-12 | F67: 0.12 | G67: ACEITE DE VASELINA GL.QF | H67: 1.96 | I67: =+IF(F67=0%,D67*H67,0) -> 0 | J67: =+IF(F67=12%,D67*H67,0) -> 117.6 | K67: 0 | L67: 0 | M67: =+J67*K67 -> 0 | N67: =+(J67-M67)*F67 -> 14.112 | O67: =+J67-M67+N67 -> 131.712 | P67: INVENTARIO | Q67: 1.1.02.04.001 | R67: INVENTARIO | S67: 1.45 | T67: 21.75
B68: tpIdCliente | C68: 05 | D68: 32.77 | E68: 396-2507 | F68: 0.12 | G68: Bastidor | H68: 4 | I68: =+IF(F68=0%,D68*H68,0) -> 0 | J68: =+IF(F68=12%,D68*H68,0) -> 131.08 | K68: 0 | L68: 0 | M68: =+J68*K68 -> 0 | N68: =+(J68-M68)*F68 -> 15.7296 | O68: =+J68-M68+N68 -> 146.8096 | P68: INVENTARIO | Q68: 1.1.02.04.001 | R68: INVENTARIO | S68: 2.96 | T68: 36.6152
B69: Tipo de Comprobante | C69: Documentos autorizados utilizados en ventas excepto N/C N/D | D69: 12 | E69: 396-306 | F69: 0.12 | G69: Tira Color Dorado Con Filos Negros De 7.5 Ancho | H69: 4.39 | I69: =+IF(F69=0%,D69*H69,0) -> 0 | J69: =+IF(F69=12%,D69*H69,0) -> 52.68 | K69: 0 | L69: 0 | M69: =+J69*K69 -> 0 | N69: =+(J69-M69)*F69 -> 6.3216 | O69: =+J69-M69+N69 -> 59.0016 | P69: INVENTARIO | Q69: 1.1.02.04.001 | R69: INVENTARIO | S69: 3.25 | T69: 72.995
B70: tipoComprobante | C70: 18 | D70: 10.99 | E70: 362-2889 | F70: 0.12 | G70: Blanca Estucada Semimate | H70: 1.69 | I70: =+IF(F70=0%,D70*H70,0) -> 0 | J70: =+IF(F70=12%,D70*H70,0) -> 18.5731 | K70: 0 | L70: 0 | M70: =+J70*K70 -> 0 | N70: =+(J70-M70)*F70 -> 2.228772 | O70: =+J70-M70+N70 -> 20.801872 | P70: INVENTARIO | Q70: 1.1.02.04.001 | R70: INVENTARIO | S70: 1.25 | T70: 10.8375
B71: Tipo de Emisión | C71: Factura Fisica
B72: tipoEm | C72: f | T72: 142.1977
B73: Fecha Emi | C73: 43513 | D73: SUBTOTAL 0% | E73: =+SUM(I67:I70) -> 0
B74: Establecimiento | C74: 001 | D74: SUBTOTAL 12% | E74: =+SUM(J67:J72) -> 319.9331
B75: Punto Emision | C75: 001 | D75: DESCUENTO | E75: =SUM(M67:M72) -> 0
B76: Secuencial | C76: 102 | D76: IVA | E76: =SUM(N67:N72) -> 38.391972
D77: TOTAL | E77: =SUM(O67:O72) -> 358.32507
B80: RETENCION FACTURA VENTA
B81: Establecimiento Ret1 | C81: 001 | D81: CONTABILIDAD | E81: CUENTA CONT. | G81: BASE IMPONIBLE | H81: IMPUESTO | J81: PORCENTAJE RETENCION | L81: VALOR RET. | M81: TOTAL RET | N81: TOTAL FACT - RET
B82: Pto Emision Ret1 | C82: 001 | D82: 2.1.01.07.004 | E82: Retención IVA 50% | G82: 727 | H82: IVA | J82: 0.5 | L82: =+E76*J82 -> 19.195986 | M82: =+L82+L83 -> 25.594648 | N82: =+E77-M82 -> 332.73042
B83: Secuencial Ret 1 | C83: 503 | D83: 2.1.01.06.002 | E83: Retención en la fuente 2% | G83: 344 | H83: RENTA | J83: 0.02 | L83: =(E74+E73-E75)*J83 -> 6.398662
B84: Autorizacion | C84: 1123134181
B85: Nro Factura | C85: =+CONCATENATE(C74,"-",C75,"-",C76) -> 001-001-102
B86: Fecha | C86: =+C73 -> 43513 | E86: ASIENTO DIARIO
B87: Tipo de Desgloce | C87: Normal | E87: KARDEX
B88: Boton | C88: Tarjeta de Credito
B89: Cuenta Contable | C89: Sociedades Financieras
B90: Valor a pagar | C90: =+E77-M82 -> 332.73042
B91: Estado | C91: Emitido
A93: I-SD-R | B93: MX 1 OP | C93: FACTURA VENTA # 4
B94: FACTURA VENTA
B95: Proveedor | C95: ILUMAX | D95: CANT | E95: CODIGO | F95: IVA | G95: PRODUCTO/DESCRIP | H95: P. UNI | I95: SUBT 0% | J95: SUBT 12% | K95: DESC % | L95: DESC $ | M95: DESC TOTAL | N95: IVA | O95: TOTAL | P95: CONTABILIDAD | Q95: NRO CUENTA | R95: TIPO
B96: idProv | C96: 1708492408001 | D96: 118.47 | E96: I006 | F96: 0.12 | G96: Azúl Con Dorado | H96: 1.47 | I96: =+IF(F96=0%,D96*H96,0) -> 0 | J96: =+IF(F96=12%,D96*H96,0) -> 174.1509 | K96: 0 | L96: 0 | M96: =+J96*K96 -> 0 | N96: =+(J96-M96)*F96 -> 20.898108 | O96: =+J96-M96+N96 -> 195.04901 | P96: INVENTARIO | Q96: 1.1.02.04.001 | R96: INVENTARIO
B97: tpIdProv | C97: 01 | D97: 249.58 | E97: I007 | F97: 0.12 | G97: pino natural procesado con ceja izq | H97: 2.96 | I97: =+IF(F97=0%,D97*H97,0) -> 0 | J97: =+IF(F97=12%,D97*H97,0) -> 738.7568 | K97: 0 | L97: 0 | M97: =+J97*K97 -> 0 | N97: =+(J97-M97)*F97 -> 88.650816 | O97: =+J97-M97+N97 -> 827.40762 | P97: INVENTARIO | Q97: 1.1.02.04.001 | R97: INVENTARIO
B98: Sustento T | C98: INVENTARIO CREDITO TRIBUTARIO PARA DECLARACION DE IVA | D98: 73.54 | E98: I008 | F98: 0.12 | G98: pino natural peq. Procesado ceja | H98: 3.15 | I98: =+IF(F98=0%,D98*H98,0) -> 0 | J98: =+IF(F98=12%,D98*H98,0) -> 231.651 | K98: 0 | L98: 0 | M98: =+J98*K98 -> 0 | N98: =+(J98-M98)*F98 -> 27.79812 | O98: =+J98-M98+N98 -> 259.44912 | P98: INVENTARIO | Q98: 1.1.02.04.001 | R98: INVENTARIO
B99: codSustento | C99: 06 | D99: 29 | E99: I009 | F99: 0.12 | G99: pino natural procesado con ceja der | H99: 1.25 | I99: =+IF(F99=0%,D99*H99,0) -> 0 | J99: =+IF(F99=12%,D99*H99,0) -> 36.25 | K99: 0 | L99: 0 | M99: =+J99*K99 -> 0 | N99: =+(J99-M99)*F99 -> 4.35 | O99: =+J99-M99+N99 -> 40.6 | P99: INVENTARIO | Q99: 1.1.02.04.001 | R99: INVENTARIO
B100: Tipo Comp Aut | C100: FACTURA
B101: tipoComprobante | C101: 1
B102: autorizacion | C102: 1122728319 | D102: SUBTOTAL 0% | E102: =+SUM(I96:I99) -> 0
B103: Fecha Emi | C103: 43513 | D103: SUBTOTAL 12% | E103: =+SUM(J96:J101) -> 1180.8087
B104: Establecimiento | C104: 001 | D104: DESCUENTO | E104: =SUM(M96:M101) -> 0
B105: Punto Emision | C105: 001 | D105: IVA | E105: =SUM(N96:N101) -> 141.69704
B106: Secuencial | C106: 103 | D106: TOTAL | E106: =SUM(O96:O101) -> 1322.5057
B109: RETENCION FACTURA VENTA
B110: Establecimiento Ret1 | C110: 001 | D110: CONTABILIDAD | E110: CUENTA CONT. | G110: BASE IMPONIBLE | H110: IMPUESTO | J110: PORCENTAJE RETENCION | L110: VALOR RET. | M110: TOTAL RET | N110: TOTAL FACT - RET
B111: Pto Emision Ret1 | C111: 001 | D111: 2.1.01.07.005 | E111: Retención IVA 70% | G111: 729 | H111: IVA | J111: 0.7 | L111: =+E105*J111 -> 99.187931 | M111: =+L111+L112 -> 110.99602 | N111: =+E106-M111 -> 1211.5097
B112: Secuencial Ret 1 | C112: 504 | D112: 2.1.01.06.001 | E112: Retención en la fuente 1% | G112: 312 | H112: RENTA | J112: 0.01 | L112: =(E103+E102-E104)*J112 -> 11.808087
B113: Nro Factura | C113: =+CONCATENATE(C104,"-",C105,"-",C106) -> 001-001-103
...

Sheet LIBRO DIARIO
A1: ASIENTO | B1: FECHA | C1: DETALLE TRANSACCION | D1: DETALLE | E1: CUENTA CONTABLE | F1: DEBE | G1: HABER | H1: TOTAL DEBE | I1: TOTAL HABER
A2: 1 | B2: 43497 | C2: ESI AL 1 DE FEBRERO DEL 2019 | D2: Banco XXXXX XXXXX | E2: 1.1.01.02.001 | F2: 1200 | H2: 41669.976 | I2: 41669.976
D3: Inventario | E3: 1.1.02.04.001 | F3: 26769.976
D4: Terrenos | E4: 1.2.01.03.001 | F4: 12500
D5: Equipo de oficina | E5: 1.2.01.01.001 | F5: 1200
D6: Cuentas por Pagar | E6: 2.1.01.01.002 | G6: 400
D7: Préstamos bancarios | E7: 2.1.01.04.001 | G7: 3000
D8: Capital | E8: 3.1.01.01.001 | G8: 38269.976
A9: 2 | B9: =+[1]COMPRAS!B16 -> 43497 | C9: =+[1]COMPRAS!B6 -> FACTURA COMPRA # 1 | D9: Inventario | E9: 1.1.02.04.001 | F9: =+COMPRAS!E16+COMPRAS!E15-COMPRAS!E17 -> 424.4316 | H9: =+SUM(F9:F13) -> 475.36339 | I9: =+SUM(G9:G13) -> 475.36339 | J9: VOLVER A FACTURA
D10: Iva pagado | E10: 1.1.02.06.001 | F10: =+COMPRAS!E18 -> 50.931792
D11: =+COMPRAS!E24 -> Retencion IVA por pagar 100% | E11: =+COMPRAS!D24 -> 2.1.01.07.006 | G11: =+COMPRAS!L24 -> 50.931792
D12: =+COMPRAS!E25 -> Impuesto a la renta por pagar 1% | E12: =+COMPRAS!D25 -> 2.1.01.06.001 | G12: =+COMPRAS!L25 -> 4.244316
D13: Proveedores | G13: =+COMPRAS!N24 -> 420.18728
A14: 3 | B14: =+COMPRAS!C44 -> 43497 | C14: =+COMPRAS!C34 -> FACTURA COMPRA # 2 | D14: Inventario | E14: 1.1.02.04.001 | F14: =+COMPRAS!E44+COMPRAS!E43-COMPRAS!E45 -> 424.4316 | H14: =+SUM(F14:F18) -> 475.36339 | I14: =+SUM(G14:G18) -> 475.36339 | J14: VOLVER A FACTURA
D15: Iva pagado | E15: 1.1.02.06.001 | F15: =+COMPRAS!E46 -> 50.931792
D16: =+COMPRAS!E52 -> Retencion IVA por pagar 30% | E16: =+COMPRAS!D52 -> 2.1.01.07.003 | G16: =+COMPRAS!L52 -> 15.279538
D17: =+COMPRAS!E53 -> Impuesto a la renta por pagar 8% | E17: =+COMPRAS!D53 -> 2.1.01.06.003 | G17: =+COMPRAS!L53 -> 33.954528
D18: Proveedores | G18: =+COMPRAS!N52 -> 426.12933
A19: 4 | B19: =+B14 -> 43497 | C19: =+C14 -> FACTURA COMPRA # 2 | D19: Proveedores | F19: =+G18 -> 426.12933 | H19: =+SUM(F19:F20) -> 426.12933 | I19: =+SUM(G19:G20) -> 426.12933
D20: =+COMPRAS!C58 -> Caja General | G20: =+COMPRAS!C59 -> 426.12933
A21: 5 | B21: =+COMPRAS!C72 -> 43497 | C21: =+COMPRAS!C62 -> FACTURA COMPRA # 3 | D21: Inventario | E21: 1.1.02.04.001 | F21: =+COMPRAS!E72+COMPRAS!E71-COMPRAS!E73 -> 424.4316 | H21: =+SUM(F21:F25) -> 475.36339 | I21: =+SUM(G21:G25) -> 475.36339 | J21: VOLVER A FACTURA
D22: Iva pagado | E22: 1.1.02.06.001 | F22: =+COMPRAS!E74 -> 50.931792
D23: =+COMPRAS!E80 -> Retencion IVA por pagar 50% | E23: =+COMPRAS!D80 -> 2.1.01.07.004 | G23: =+COMPRAS!L80 -> 25.465896
D24: =+COMPRAS!E81 -> Impuesto a la renta por pagar 2% | E24: =+COMPRAS!D81 -> 2.1.01.06.002 | G24: =+COMPRAS!L81 -> 8.488632
D25: Proveedores | E25: 2.1.01.01.001 | G25: =+COMPRAS!N80 -> 441.40886
A26: 6 | B26: =+B21 -> 43497 | C26: =+C21 -> FACTURA COMPRA # 3 | D26: Proveedores | E26: 2.1.01.01.001 | F26: =+G25 -> 441.40886 | H26: =+SUM(F26:F27) -> 441.40886 | I26: =+SUM(G26:G27) -> 441.40886
D27: Tarjetas de Credito | E27: 5.2.01.10.001 | G27: =+COMPRAS!C87 -> 441.40886
A28: 7 | B28: =+COMPRAS!C100 -> 43498 | C28: =+COMPRAS!C90 -> FACTURA COMPRA # 4 | D28: Inventario | E28: 1.1.02.04.001 | F28: =+COMPRAS!E99+COMPRAS!E100-COMPRAS!E101 -> 1180.8087 | H28: =+SUM(F28:F32) -> 1322.5057 | I28: =+SUM(G28:G32) -> 1322.5057 | J28: VOLVER A FACTURA
D29: Iva pagado | E29: 1.1.02.06.001 | F29: =+COMPRAS!E102 -> 141.69704
D30: =+COMPRAS!E108 -> Retencion IVA por pagar 70% | E30: =+COMPRAS!D108 -> 2.1.01.07.005 | G30: =+COMPRAS!L108 -> 99.187931
D31: =+COMPRAS!E109 -> Impuesto a la renta por pagar 1% | E31: =+COMPRAS!D109 -> 2.1.01.06.001 | G31: =+COMPRAS!L109 -> 11.808087
D32: Proveedores | G32: =+COMPRAS!N108 -> 1211.5097
A33: 8 | B33: =+B28 -> 43498 | C33: =+C28 -> FACTURA COMPRA # 4 | D33: Proveedores | F33: =+G32 -> 1211.5097 | H33: =+SUM(F33:F34) -> 1211.5097 | I33: =+SUM(G33:G34) -> 1211.5097
D34: =+COMPRAS!C114 -> Bancos XXX XXXX | G34: =+COMPRAS!C115 -> 1211.5097
A35: 9 | B35: =+COMPRAS!C128 -> 43498 | C35: =+COMPRAS!C118 -> FACTURA COMPRA # 5 | D35: Inventario | E35: 1.1.02.04.001 | F35: =+COMPRAS!E127+COMPRAS!E128-COMPRAS!E129 -> 1180.8087 | H35: =+SUM(F35:F39) -> 1322.5057 | I35: =+SUM(G35:G39) -> 1322.5057 | J35: VOLVER A FACTURA
D36: Iva pagado | E36: 1.1.02.06.001 | F36: =+COMPRAS!E130 -> 141.69704
D37: =+COMPRAS!E136 -> Retencion IVA por pagar 10% | E37: =+COMPRAS!D136 -> 2.1.01.07.001 | G37: =+COMPRAS!L136 -> 14.169704
D38: =+COMPRAS!E137 -> Impuesto a la renta por pagar 8% | E38: =+COMPRAS!D137 -> 2.1.01.06.003 | G38: =+COMPRAS!L137 -> 94.464696
D39: Proveedores | G39: =+COMPRAS!N136 -> 1213.8713
A40: 10 | B40: =+B35 -> 43498 | C40: =+C35 -> FACTURA COMPRA # 5 | D40: Proveedores | F40: =+G39 -> 1213.8713 | H40: =+SUM(F40:F43) -> 1213.8713 | I40: =+SUM(G40:G43) -> 1213.8713
D41: =+COMPRAS!C142 -> Bancos XXX XXXX | G41: =+COMPRAS!C143 -> 364.1614
D42: =+COMPRAS!C144 -> Bancos XYZ XYZ | G42: =+COMPRAS!C145 -> 364.1614
D43: =+COMPRAS!C147 -> Caja General | G43: =+COMPRAS!C148 -> 485.54854
A44: 11 | B44: =+COMPRAS!C161 -> 43498 | C44: =+COMPRAS!C151 -> FACTURA COMPRA # 6 | D44: Inventario | E44: 1.1.02.04.001 | F44: =+COMPRAS!E160+COMPRAS!E161-COMPRAS!E162 -> 1180.8087 | H44: =+SUM(F44:F48) -> 1322.5057 | I44: =+SUM(G44:G48) -> 1322.5057 | J44: VOLVER A FACTURA
D45: Iva pagado | E45: 1.1.02.06.001 | F45: =+COMPRAS!E163 -> 141.69704
D46: =+COMPRAS!E169 -> Retencion IVA por pagar 20% | E46: =+COMPRAS!D169 -> 2.1.01.07.002 | G46: =+COMPRAS!L169 -> 28.339409
D47: =+COMPRAS!E170 -> Impuesto a la renta por pagar 2% | E47: =+COMPRAS!D170 -> 2.1.01.06.002 | G47: =+COMPRAS!L170 -> 23.616174
D48: Proveedores | G48: =+COMPRAS!N169 -> 1270.5502
A49: 12 | B49: =+B44 -> 43498 | C49: =+C44 -> FACTURA COMPRA # 6 | D49: Proveedores | F49: =+COMPRAS!C176 -> 762.3301 | H49: =+SUM(F49:F50) -> 762.3301 | I49: =+SUM(G49:G50) -> 762.3301
D50: =+COMPRAS!C175 -> Bancos XXX XXXX | G50: =+COMPRAS!C176 -> 762.3301
A51: 13 | B51: =+COMPRAS!C192 -> 43497 | C51: =+COMPRAS!C182 -> FACTURA COMPRA # 7 | D51: Inventario | E51: 1.1.02.04.001 | F51: =+COMPRAS!E191+COMPRAS!E192-COMPRAS!E193 -> 424.4316 | H51: =+SUM(F51:F53) -> 475.36339 | I51: =+SUM(G51:G53) -> 475.36339 | J51: VOLVER A FACTURA
D52: Iva pagado | E52: 1.1.02.06.001 | F52: =+COMPRAS!E194 -> 50.931792
D53: Proveedores | G53: =+COMPRAS!E195 -> 475.36339
A54: 14 | B54: =+COMPRAS!C215 -> 43497 | C54: =+COMPRAS!C205 -> FACTURA COMPRA # 8 | D54: Inventario | E54: 1.1.02.04.001 | F54: =+COMPRAS!E214+COMPRAS!E215-COMPRAS!E216 -> 501.8516 | H54: =+SUM(F54:F56) -> 562.07379 | I54: =+SUM(G54:G56) -> 562.07379 | J54: VOLVER A FACTURA
D55: Iva pagado | E55: 1.1.02.06.001 | F55: =+COMPRAS!E217 -> 60.222192
D56: Proveedores | G56: =+COMPRAS!E218 -> 562.07379
A57: 15 | B57: =+B54 -> 43497 | C57: =+C54 -> FACTURA COMPRA # 8 | D57: Proveedores | F57: =+COMPRAS!E218 -> 562.07379 | H57: =+SUM(F57:F58) -> 562.07379 | I57: =+SUM(G57:G58) -> 562.07379
D58: =+COMPRAS!C224 -> Caja General | G58: =+COMPRAS!C225 -> 562.07379
A59: 16 | B59: =+COMPRAS!C238 -> 43497 | C59: =+COMPRAS!C228 -> FACTURA COMPRA # 9 | D59: Inventario | E59: 1.1.02.04.001 | F59: =+COMPRAS!E237+COMPRAS!E238-COMPRAS!E239 -> 405.8116 | H59: =+SUM(F59:F61) -> 454.50899 | I59: =+SUM(G59:G61) -> 454.50899 | J59: VOLVER A FACTURA
D60: Iva pagado | E60: 1.1.02.06.001 | F60: =+COMPRAS!E240 -> 48.697392
D61: Proveedores | G61: =+COMPRAS!E241 -> 454.50899
A62: 17 | B62: =+B59 -> 43497 | C62: =+C59 -> FACTURA COMPRA # 9 | D62: Proveedores | F62: =+G61 -> 454.50899 | H62: =+SUM(F62:F63) -> 454.50899 | I62: =+SUM(G62:G63) -> 454.50899
D63: Tarjetas de Credito | E63: 5.2.01.10.001 | G63: =+COMPRAS!C248 -> 454.50899
A64: 18 | B64: =+COMPRAS!C261 -> 43498 | C64: =+COMPRAS!C251 -> FACTURA COMPRA # 10 | D64: Inventario | E64: 1.1.02.04.001 | F64: =+COMPRAS!E260+COMPRAS!E261-COMPRAS!E262 -> 1180.8087 | H64: =+SUM(F64:F66) -> 1322.5057 | I64: =+SUM(G64:G66) -> 1322.5057 | J64: VOLVER A FACTURA
D65: Iva pagado | E65: 1.1.02.06.001 | F65: =+COMPRAS!E263 -> 141.69704
D66: Proveedores | G66: =+COMPRAS!E264 -> 1322.5057
A67: 19 | B67: =+B64 -> 43498 | C67: =+C64 -> FACTURA COMPRA # 10 | D67: Proveedores | F67: =+G66 -> 1322.5057 | H67: =+SUM(F67:F68) -> 1322.5057 | I67: =+SUM(G67:G68) -> 1322.5057
D68: =+COMPRAS!C270 -> Bancos XXX XXXX | G68: =+COMPRAS!C271 -> 1322.5057
A69: 20 | B69: =+COMPRAS!C284 -> 43498 | C69: =+COMPRAS!C274 -> FACTURA COMPRA # 11 | D69: Inventario | E69: 1.1.02.04.001 | F69: =+COMPRAS!E283+COMPRAS!E284-COMPRAS!E285 -> 1180.8087 | H69: =+SUM(F69:F71) -> 1322.5057 | I69: =+SUM(G69:G71) -> 1322.5057 | J69: VOLVER A FACTURA
D70: Iva pagado | E70: 1.1.02.06.001 | F70: =+COMPRAS!E286 -> 141.69704
D71: Proveedores | G71: =+COMPRAS!E287 -> 1322.5057
A72: 21 | B72: =+B69 -> 43498 | C72: =+C69 -> FACTURA COMPRA # 11 | D72: Proveedores | F72: =+G71 -> 1322.5057 | H72: =+SUM(F72:F75) -> 1322.5057 | I72: =+SUM(G72:G75) -> 1322.5057
D73: =+COMPRAS!C294 -> Bancos XXX XXXX | G73: =+COMPRAS!C295 -> 396.75172
D74: =+COMPRAS!C296 -> Bancos XYZ XYZ | G74: =+COMPRAS!C297 -> 396.75172
D75: =+COMPRAS!C299 -> Caja General | G75: =+COMPRAS!C300 -> 529.0023
A76: 22 | B76: =+COMPRAS!C313 -> 43498 | C76: =+COMPRAS!C303 -> FACTURA COMPRA # 12 | D76: Inventario | E76: 1.1.02.04.001 | F76: =+COMPRAS!E312+COMPRAS!E313-COMPRAS!E314 -> 1180.8087 | H76: =+SUM(F76:F78) -> 1322.5057 | I76: =+SUM(G76:G78) -> 1322.5057 | J76: VOLVER A FACTURA
D77: Iva pagado | E77: 1.1.02.06.001 | F77: =+COMPRAS!E315 -> 141.69704
D78: Proveedores | G78: =+COMPRAS!E316 -> 1322.5057
A79: 23 | B79: =+B76 -> 43498 | C79: =+C76 -> FACTURA COMPRA # 12 | D79: =+COMPRAS!C325 -> Proveedores | F79: =+COMPRAS!C323 -> 793.50345 | H79: =+SUM(F79:F80) -> 793.50345 | I79: =+SUM(G79:G80) -> 793.50345
D80: =+COMPRAS!C322 -> Bancos XXX XXXX | G80: =+COMPRAS!C323 -> 793.50345
A81: 24 | B81: =+COMPRAS!C339 -> 43500 | C81: =+COMPRAS!C329 -> FACTURA COMPRA # 13 | D81: =+COMPRAS!P332 -> Útiles y papelería | E81: =+COMPRAS!Q332 -> 5.2.01.02.011 | F81: =+COMPRAS!E338+COMPRAS!E339+-COMPRAS!E340 -> 81.5 | H81: =+SUM(F81:F85) -> 91.28 | I81: =+SUM(G81:G85) -> 91.28 | J81: VOLVER A FACTURA
D82: Iva pagado | E82: 1.1.02.06.001 | F82: =+COMPRAS!E341 -> 9.78
D83: =+COMPRAS!E347 -> Retencion IVA por pagar 100% | E83: =+COMPRAS!D347 -> 2.1.01.07.006 | G83: =+COMPRAS!L347 -> 9.78
D84: =+COMPRAS!E348 -> Impuesto a la renta por pagar 1% | E84: =+COMPRAS!D348 -> 2.1.01.06.001 | G84: =+COMPRAS!L348 -> 0.815
D85: Proveedores | G85: =+COMPRAS!N347 -> 80.685
A86: 25 | B86: =+COMPRAS!C367 -> 43500 | C86: =+COMPRAS!C357 -> FACTURA COMPRA # 14 | D86: =+COMPRAS!P360 -> Útiles y papelería | E86: =+COMPRAS!Q360 -> 5.2.01.02.011 | F86: =+COMPRAS!E366+COMPRAS!E367-COMPRAS!E368 -> 839.46 | H86: =+SUM(F86:F90) -> 940.1952 | I86: =+SUM(G86:G90) -> 940.1952 | J86: VOLVER A FACTURA
D87: Iva pagado | E87: 1.1.02.06.001 | F87: =+COMPRAS!E369 -> 100.7352
D88: =+COMPRAS!E375 -> Retencion IVA por pagar 30% | E88: =+COMPRAS!D375 -> 2.1.01.07.003 | G88: =+COMPRAS!L375 -> 30.22056
D89: =+COMPRAS!E376 -> Impuesto a la renta por pagar 8% | E89: =+COMPRAS!D376 -> 2.1.01.06.003 | G89: =+COMPRAS!L376 -> 67.1568
D90: Proveedores | G90: =+COMPRAS!N375 -> 842.81784
A91: 26 | B91: =+B86 -> 43500 | C91: =+C86 -> FACTURA COMPRA # 14 | D91: Proveedores | F91: =+G90 -> 842.81784 | H91: =+SUM(F91:F92) -> 842.81784 | I91: =+SUM(G91:G92) -> 842.81784
D92: =+COMPRAS!C381 -> Caja General | G92: =+COMPRAS!C382 -> 842.81784
A93: 27 | B93: =+COMPRAS!C395 -> 43500 | C93: =+COMPRAS!C385 -> FACTURA COMPRA # 15 | D93: =+COMPRAS!P388 -> Útiles y papelería | E93: =+COMPRAS!Q388 -> 5.2.01.02.011 | F93: =+COMPRAS!E394+COMPRAS!E395-COMPRAS!E396 -> 81.5 | H93: =+SUM(F93:F97) -> 91.28 | I93: =+SUM(G93:G97) -> 91.28 | J93: VOLVER A FACTURA
D94: Iva pagado | E94: 1.1.02.06.001 | F94: =+COMPRAS!E397 -> 9.78
D95: =+COMPRAS!E403 -> Retencion IVA por pagar 50% | E95: =+COMPRAS!D403 -> 2.1.01.07.004 | G95: =+COMPRAS!L403 -> 4.89
D96: =+COMPRAS!E404 -> Impuesto a la renta por pagar 2% | E96: =+COMPRAS!D404 -> 2.1.01.06.002 | G96: =+COMPRAS!L404 -> 1.63
D97: Proveedores | G97: =+COMPRAS!N403 -> 84.76
A98: 28 | B98: =+B93 -> 43500 | C98: =+C93 -> FACTURA COMPRA # 15 | D98: Proveedores | F98: =+G97 -> 84.76 | H98: =+SUM(F98:F99) -> 84.76 | I98: =+SUM(G98:G99) -> 84.76
D99: =+COMPRAS!C409 -> Sociedades Financieras | G99: =+COMPRAS!C410 -> 84.76
A100: 29 | B100: =+COMPRAS!C423 -> 43501 | C100: =+COMPRAS!C413 -> FACTURA COMPRA # 16 | D100: =+COMPRAS!P416 -> Equipos de computación | E100: =+COMPRAS!Q416 -> 1.2.01.01.002 | F100: =+COMPRAS!E422+COMPRAS!E423-COMPRAS!E424 -> 840 | H100: =+SUM(F100:F104) -> 940.8 | I100: =+SUM(G100:G104) -> 940.8 | J100: VOLVER A FACTURA
...

Sheet Hoja4
A1: ASIENTO | B1: FECHA | C1: DETALLE TRANSACCION | D1: DETALLE | E1: CUENTA CONTABLE | F1: DEBE | G1: HABER | H1: TOTAL DEBE | I1: TOTAL HABER
A2: 79 | B2: =+VENTAS!C15 -> 43513 | C2: =+VENTAS!C6 -> FACTURA VENTA # 1 | D2: =+VENTAS!C31 -> Clientes | F2: =+VENTAS!N24 -> 190.21038 | H2: =+SUM(F2:F5) -> 215.1875 | I2: =+SUM(G2:G6) -> 215.1875 | J2: VOLVER A FACTURA
D3: =+VENTAS!E24 -> Retención IVA 100% | E3: =+VENTAS!D24 -> 2.1.01.07.006 | F3: =+VENTAS!L24 -> 23.055804
D4: =+VENTAS!E25 -> Retención en la fuente 1% | E4: =+VENTAS!D25 -> 2.1.01.06.001 | F4: =+VENTAS!L25 -> 1.921317
D5: Iva pagado | E5: 1.1.02.06.001 | G5: =+VENTAS!E18 -> 23.055804
D6: Ventas | G6: =+VENTAS!E15+VENTAS!E16-VENTAS!E17 -> 192.1317
A7: 80 | B7: =+B2 -> 43513 | C7: =+C2 -> FACTURA VENTA # 1 | D7: Costo de venta inventario | F7: =+VENTAS!T14 -> 141.35905 | H7: =+SUM(F7:F8) -> 141.35905 | I7: =+SUM(G7:G8) -> 141.35905
D8: Inventario | E8: 1.1.02.04.001 | G8: =+VENTAS!T14 -> 141.35905
A9: 81 | B9: =+VENTAS!C44 -> 43513 | C9: =+VENTAS!C35 -> FACTURA VENTA # 2 | D9: =+VENTAS!C31 -> Clientes | F9: =+VENTAS!N53 -> 137.47461 | H9: =+SUM(F9:F12) -> 153.35813 | I9: =+SUM(G9:G13) -> 153.35813 | J9: VOLVER A FACTURA
D10: =+VENTAS!E53 -> Retencion IVA 30% | E10: =+VENTAS!D53 -> 2.1.01.07.003 | F10: =+VENTAS!L53 -> 4.9293684
D11: =+VENTAS!E54 -> Retención en la fuente 8% | E11: =+VENTAS!D54 -> 2.1.01.06.003 | F11: =+VENTAS!L54 -> 10.954152
D12: Iva pagado | E12: 1.1.02.06.001 | G12: =+VENTAS!E47 -> 16.431228
D13: Ventas | G13: =+VENTAS!E44+VENTAS!E45-VENTAS!E46 -> 136.9269
A14: 82 | B14: =+B9 -> 43513 | C14: =+C9 -> FACTURA VENTA # 2 | D14: =+VENTAS!C60 -> Caja General | F14: =+VENTAS!C61 -> 137.47461 | H14: =+SUM(G14:G15) -> 137.47461 | I14: =+SUM(F14:F15) -> 137.47461
D15: Clientes | G15: =+F9 -> 137.47461
A16: 83 | B16: =+B14 -> 43513 | C16: =+C14 -> FACTURA VENTA # 2 | D16: Costo de venta inventario | F16: =+VENTAS!T43 -> 142.1977 | H16: =+SUM(F16:F17) -> 142.1977 | I16: =+SUM(G16:G17) -> 142.1977
D17: Inventario | E17: 1.1.02.04.001 | G17: =+VENTAS!T43 -> 142.1977
A18: 84 | B18: =+VENTAS!C73 -> 43513 | C18: =+VENTAS!C64 -> FACTURA VENTA # 3 | D18: Clientes | F18: =+VENTAS!N82 -> 332.73042 | H18: =+SUM(F18:F21) -> 358.32507 | I18: =+SUM(G18:G22) -> 358.32507 | J18: VOLVER A FACTURA
D19: =+VENTAS!E82 -> Retención IVA 50% | F19: =+VENTAS!L82 -> 19.195986
D20: =+VENTAS!E83 -> Retención en la fuente 2% | F20: =+VENTAS!L83 -> 6.398662
D21: Iva pagado | E21: 1.1.02.06.001 | G21: =+VENTAS!E76 -> 38.391972
D22: Ventas | G22: =+VENTAS!E73+VENTAS!E74-VENTAS!E75 -> 319.9331
A23: 85 | B23: =+B18 -> 43513 | C23: =+C18 -> FACTURA VENTA # 3 | D23: =+VENTAS!C88 -> Tarjeta de Credito | F23: =+VENTAS!C90 -> 332.73042 | H23: =+SUM(G23:G24) -> 332.73042 | I23: =+SUM(F23:F24) -> 332.73042
D24: Clientes | G24: =+VENTAS!C90 -> 332.73042
A25: 86 | B25: =+B23 -> 43513 | C25: =+C23 -> FACTURA VENTA # 3 | D25: Costo de venta inventario | F25: =+VENTAS!T72 -> 142.1977 | H25: =+SUM(F25:F26) -> 142.1977 | I25: =+SUM(G25:G26) -> 142.1977
D26: Inventario | E26: 1.1.02.04.001 | G26: =+VENTAS!T72 -> 142.1977
A27: 7 | B27: =+VENTAS!C103 -> 43513 | C27: =+VENTAS!C93 -> FACTURA VENTA # 4 | D27: Inventario | E27: 1.1.02.04.001 | G27: =+VENTAS!E102+VENTAS!E103-VENTAS!E104 -> 1180.8087 | H27: =+SUM(G27:G31) -> 1322.5057 | I27: =+SUM(F27:F31) -> 1322.5057 | J27: VOLVER A FACTURA
D28: Iva pagado | E28: 1.1.02.06.001 | G28: =+VENTAS!E105 -> 141.69704
D29: =+VENTAS!E111 -> Retención IVA 70% | E29: =+VENTAS!D111 -> 2.1.01.07.005 | F29: =+VENTAS!L111 -> 99.187931
D30: =+VENTAS!E112 -> Retención en la fuente 1% | E30: =+VENTAS!D112 -> 2.1.01.06.001 | F30: =+VENTAS!L112 -> 11.808087
D31: Proveedores | F31: =+VENTAS!N111 -> 1211.5097
A32: 8 | B32: =+B27 -> 43513 | C32: =+C27 -> FACTURA VENTA # 4 | D32: Proveedores | G32: =+F31 -> 1211.5097 | H32: =+SUM(G32:G33) -> 1211.5097 | I32: =+SUM(F32:F33) -> 1211.5097
D33: =+VENTAS!C117 -> Bancos XXX XXXX | F33: =+VENTAS!C118 -> 1211.5097
A34: 9 | B34: =+VENTAS!C131 -> 43513 | C34: =+VENTAS!C121 -> FACTURA VENTA # 5 | D34: Inventario | E34: 1.1.02.04.001 | G34: =+VENTAS!E130+VENTAS!E131-VENTAS!E132 -> 1180.8087 | H34: =+SUM(G34:G38) -> 1322.5057 | I34: =+SUM(F34:F38) -> 1322.5057 | J34: VOLVER A FACTURA
D35: Iva pagado | E35: 1.1.02.06.001 | G35: =+VENTAS!E133 -> 141.69704
D36: =+VENTAS!E139 -> Retención IVA 10% | E36: =+VENTAS!D139 -> 2.1.01.07.001 | F36: =+VENTAS!L139 -> 14.169704
D37: =+VENTAS!E140 -> Retención en la fuente 8% | E37: =+VENTAS!D140 -> 2.1.01.06.003 | F37: =+VENTAS!L140 -> 94.464696
D38: Proveedores | F38: =+VENTAS!N139 -> 1213.8713
A39: 10 | B39: =+B34 -> 43513 | C39: =+C34 -> FACTURA VENTA # 5 | D39: Proveedores | G39: =+F38 -> 1213.8713 | H39: =+SUM(G39:G42) -> 1213.8713 | I39: =+SUM(F39:F42) -> 1213.8713
D40: =+VENTAS!C145 -> Bancos XXX XXXX | F40: =+VENTAS!C146 -> 364.1614
D41: =+VENTAS!C147 -> Bancos XYZ XYZ | F41: =+VENTAS!C148 -> 364.1614
D42: =+VENTAS!C150 -> Caja General | F42: =+VENTAS!C151 -> 485.54854
A43: 11 | B43: =+VENTAS!C164 -> 43513 | C43: =+VENTAS!C154 -> FACTURA VENTA # 6 | D43: Inventario | E43: 1.1.02.04.001 | G43: =+VENTAS!E163+VENTAS!E164-VENTAS!E165 -> 1180.8087 | H43: =+SUM(G43:G47) -> 1322.5057 | I43: =+SUM(F43:F47) -> 1322.5057 | J43: VOLVER A FACTURA
D44: Iva pagado | E44: 1.1.02.06.001 | G44: =+VENTAS!E166 -> 141.69704
D45: =+VENTAS!E172 -> Retención IVA 20% | E45: =+VENTAS!D172 -> 2.1.01.07.002 | F45: =+VENTAS!L172 -> 28.339409
D46: =+VENTAS!E173 -> Retención en la fuente 2% | E46: =+VENTAS!D173 -> 2.1.01.06.002 | F46: =+VENTAS!L173 -> 23.616174
D47: Proveedores | F47: =+VENTAS!N172 -> 1270.5502
A48: 12 | B48: =+B43 -> 43513 | C48: =+C43 -> FACTURA VENTA # 6 | D48: Proveedores | G48: =+VENTAS!C179 -> 762.3301 | H48: =+SUM(G48:G49) -> 762.3301 | I48: =+SUM(F48:F49) -> 762.3301
D49: =+VENTAS!C178 -> Bancos XXX XXXX | F49: =+VENTAS!C179 -> 762.3301
A50: 13 | B50: =+VENTAS!C195 -> 43514 | C50: =+VENTAS!C185 -> FACTURA VENTA # 7 | D50: Inventario | E50: 1.1.02.04.001 | G50: =+VENTAS!E194+VENTAS!E195-VENTAS!E196 -> 424.4316 | H50: =+SUM(G50:G52) -> 475.36339 | I50: =+SUM(F50:F52) -> 475.36339 | J50: VOLVER A FACTURA
D51: Iva pagado | E51: 1.1.02.06.001 | G51: =+VENTAS!E197 -> 50.931792
D52: Proveedores | F52: =+VENTAS!E198 -> 475.36339
A53: 14 | B53: =+VENTAS!C218 -> 43514 | C53: =+VENTAS!C208 -> FACTURA VENTA # 8 | D53: Inventario | E53: 1.1.02.04.001 | G53: =+VENTAS!E217+VENTAS!E218-VENTAS!E219 -> 501.8516 | H53: =+SUM(G53:G55) -> 562.07379 | I53: =+SUM(F53:F55) -> 562.07379 | J53: VOLVER A FACTURA
D54: Iva pagado | E54: 1.1.02.06.001 | G54: =+VENTAS!E220 -> 60.222192
D55: Proveedores | F55: =+VENTAS!E221 -> 562.07379
A56: 15 | B56: =+B53 -> 43514 | C56: =+C53 -> FACTURA VENTA # 8 | D56: Proveedores | G56: =+VENTAS!E221 -> 562.07379 | H56: =+SUM(G56:G57) -> 562.07379 | I56: =+SUM(F56:F57) -> 562.07379
D57: =+VENTAS!C227 -> Caja General | F57: =+VENTAS!C228 -> 562.07379
A58: 16 | B58: =+VENTAS!C241 -> 43514 | C58: =+VENTAS!C231 -> FACTURA VENTA # 9 | D58: Inventario | E58: 1.1.02.04.001 | G58: =+VENTAS!E240+VENTAS!E241-VENTAS!E242 -> 405.8116 | H58: =+SUM(G58:G60) -> 454.50899 | I58: =+SUM(F58:F60) -> 454.50899 | J58: VOLVER A FACTURA
D59: Iva pagado | E59: 1.1.02.06.001 | G59: =+VENTAS!E243 -> 48.697392
D60: Proveedores | F60: =+VENTAS!E244 -> 454.50899
A61: 17 | B61: =+B58 -> 43514 | C61: =+C58 -> FACTURA VENTA # 9 | D61: Proveedores | G61: =+F60 -> 454.50899 | H61: =+SUM(G61:G62) -> 454.50899 | I61: =+SUM(F61:F62) -> 454.50899
D62: Tarjetas de Credito | E62: 5.2.01.10.001 | F62: =+VENTAS!C251 -> 454.50899
A63: 18 | B63: =+VENTAS!C264 -> 43514 | C63: =+VENTAS!C254 -> FACTURA VENTA # 10 | D63: Inventario | E63: 1.1.02.04.001 | G63: =+VENTAS!E263+VENTAS!E264-VENTAS!E265 -> 1180.8087 | H63: =+SUM(G63:G65) -> 1322.5057 | I63: =+SUM(F63:F65) -> 1322.5057 | J63: VOLVER A FACTURA
D64: Iva pagado | E64: 1.1.02.06.001 | G64: =+VENTAS!E266 -> 141.69704
D65: Proveedores | F65: =+VENTAS!E267 -> 1322.5057
A66: 19 | B66: =+B63 -> 43514 | C66: =+C63 -> FACTURA VENTA # 10 | D66: Proveedores | G66: =+F65 -> 1322.5057 | H66: =+SUM(G66:G67) -> 1322.5057 | I66: =+SUM(F66:F67) -> 1322.5057
D67: =+VENTAS!C273 -> Bancos XXX XXXX | F67: =+VENTAS!C274 -> 1322.5057
A68: 20 | B68: =+VENTAS!C287 -> 43514 | C68: =+VENTAS!C277 -> FACTURA VENTA # 11 | D68: Inventario | E68: 1.1.02.04.001 | G68: =+VENTAS!E286+VENTAS!E287-VENTAS!E288 -> 1180.8087 | H68: =+SUM(G68:G70) -> 1322.5057 | I68: =+SUM(F68:F70) -> 1322.5057 | J68: VOLVER A FACTURA
D69: Iva pagado | E69: 1.1.02.06.001 | G69: =+VENTAS!E289 -> 141.69704
D70: Proveedores | F70: =+VENTAS!E290 -> 1322.5057
A71: 21 | B71: =+B68 -> 43514 | C71: =+C68 -> FACTURA VENTA # 11 | D71: Proveedores | G71: =+F70 -> 1322.5057 | H71: =+SUM(G71:G74) -> 1322.5057 | I71: =+SUM(F71:F74) -> 1322.5057
D72: =+VENTAS!C297 -> Bancos XXX XXXX | F72: =+VENTAS!C298 -> 396.75172
D73: =+VENTAS!C299 -> Bancos XYZ XYZ | F73: =+VENTAS!C300 -> 396.75172
D74: =+VENTAS!C302 -> Caja General | F74: =+VENTAS!C303 -> 529.0023
A75: 22 | B75: =+VENTAS!C316 -> 43514 | C75: =+VENTAS!C306 -> FACTURA VENTA # 12 | D75: Inventario | E75: 1.1.02.04.001 | G75: =+VENTAS!E315+VENTAS!E316-VENTAS!E317 -> 1180.8087 | H75: =+SUM(G75:G77) -> 1322.5057 | I75: =+SUM(F75:F77) -> 1322.5057 | J75: VOLVER A FACTURA
D76: Iva pagado | E76: 1.1.02.06.001 | G76: =+VENTAS!E318 -> 141.69704
D77: Proveedores | F77: =+VENTAS!E319 -> 1322.5057
A78: 23 | B78: =+B75 -> 43514 | C78: =+C75 -> FACTURA VENTA # 12 | D78: =+VENTAS!C328 -> Proveedores | G78: =+VENTAS!C326 -> 793.50345 | H78: =+SUM(G78:G79) -> 793.50345 | I78: =+SUM(F78:F79) -> 793.50345
D79: =+VENTAS!C325 -> Bancos XXX XXXX | F79: =+VENTAS!C326 -> 793.50345
A80: 24 | B80: =+VENTAS!C342 -> 43500 | C80: =+VENTAS!C332 -> FACTURA VENTA # 13 | D80: =+VENTAS!P335 -> Útiles y papelería | E80: =+VENTAS!Q335 -> 5.2.01.02.011 | G80: =+VENTAS!E341+VENTAS!E342+-VENTAS!E343 -> 81.5 | H80: =+SUM(G80:G84) -> 91.28 | I80: =+SUM(F80:F84) -> 91.28 | J80: VOLVER A FACTURA
D81: Iva pagado | E81: 1.1.02.06.001 | G81: =+VENTAS!E344 -> 9.78
D82: =+VENTAS!E350 -> Retención IVA 100% | E82: =+VENTAS!D350 -> 2.1.01.07.006 | F82: =+VENTAS!L350 -> 9.78
D83: =+VENTAS!E351 -> Retención en la fuente 1% | E83: =+VENTAS!D351 -> 2.1.01.06.001 | F83: =+VENTAS!L351 -> 0.815
D84: Proveedores | F84: =+VENTAS!N350 -> 80.685
A85: 25 | B85: =+VENTAS!C370 -> 43500 | C85: =+VENTAS!C360 -> FACTURA VENTA # 14 | D85: =+VENTAS!P363 -> Útiles y papelería | E85: =+VENTAS!Q363 -> 5.2.01.02.011 | G85: =+VENTAS!E369+VENTAS!E370-VENTAS!E371 -> 839.46 | H85: =+SUM(G85:G89) -> 940.1952 | I85: =+SUM(F85:F89) -> 940.1952 | J85: VOLVER A FACTURA
D86: Iva pagado | E86: 1.1.02.06.001 | G86: =+VENTAS!E372 -> 100.7352
D87: =+VENTAS!E378 -> Retención IVA 30% | E87: =+VENTAS!D378 -> 2.1.01.07.003 | F87: =+VENTAS!L378 -> 30.22056
D88: =+VENTAS!E379 -> Retención en la fuente 8% | E88: =+VENTAS!D379 -> 2.1.01.06.003 | F88: =+VENTAS!L379 -> 67.1568
D89: Proveedores | F89: =+VENTAS!N378 -> 842.81784
A90: 26 | B90: =+B85 -> 43500 | C90: =+C85 -> FACTURA VENTA # 14 | D90: Proveedores | G90: =+F89 -> 842.81784 | H90: =+SUM(G90:G91) -> 842.81784 | I90: =+SUM(F90:F91) -> 842.81784
D91: =+VENTAS!C384 -> Caja General | F91: =+VENTAS!C385 -> 842.81784
A92: 27 | B92: =+VENTAS!C398 -> 43500 | C92: =+VENTAS!C388 -> FACTURA VENTA # 15 | D92: =+VENTAS!P391 -> Útiles y papelería | E92: =+VENTAS!Q391 -> 5.2.01.02.011 | G92: =+VENTAS!E397+VENTAS!E398-VENTAS!E399 -> 81.5 | H92: =+SUM(G92:G96) -> 91.28 | I92: =+SUM(F92:F96) -> 91.28 | J92: VOLVER A FACTURA
D93: Iva pagado | E93: 1.1.02.06.001 | G93: =+VENTAS!E400 -> 9.78
D94: =+VENTAS!E406 -> Retención IVA 50% | E94: =+VENTAS!D406 -> 2.1.01.07.004 | F94: =+VENTAS!L406 -> 4.89
D95: =+VENTAS!E407 -> Retención en la fuente 2% | E95: =+VENTAS!D407 -> 2.1.01.06.002 | F95: =+VENTAS!L407 -> 1.63
D96: Proveedores | F96: =+VENTAS!N406 -> 84.76
A97: 28 | B97: =+B92 -> 43500 | C97: =+C92 -> FACTURA VENTA # 15 | D97: Proveedores | G97: =+F96 -> 84.76 | H97: =+SUM(G97:G98) -> 84.76 | I97: =+SUM(F97:F98) -> 84.76
D98: =+VENTAS!C412 -> Sociedades Financieras | F98: =+VENTAS!C413 -> 84.76
A99: 29 | B99: =+VENTAS!C426 -> 43501 | C99: =+VENTAS!C416 -> FACTURA VENTA # 16 | D99: =+VENTAS!P419 -> Equipos de computación | E99: =+VENTAS!Q419 -> 1.2.01.01.002 | G99: =+VENTAS!E425+VENTAS!E426-VENTAS!E427 -> 840 | H99: =+SUM(G99:G103) -> 940.8 | I99: =+SUM(F99:F103) -> 940.8 | J99: VOLVER A FACTURA
D100: Iva pagado | E100: 1.1.02.06.001 | G100: =+VENTAS!E428 -> 100.8
...

Sheet KARDEX
D1: INGRESO | G1: EGRESO | J1: SALDOS
A2: FECHA | B2: DETALLE TRANSACCION | C2: DETALLE | D2: CANT | E2: VALOR | F2: TOTAL | G2: CANT | H2: VALOR | I2: TOTAL | J2: CANT | K2: VALOR | L2: TOTAL
A3: =+[1]COMPRAS!B153 -> 43504 | B3: =+CONCATENATE(COMPRAS!C6," ",COMPRAS!C26) -> FACTURA COMPRA # 1 001-001-100 | C3: =+COMPRAS!G9 -> ACEITE DE VASELINA GL.QF | D3: =+COMPRAS!D9 -> 61 | E3: =+COMPRAS!H9 -> 1.45 | F3: =+D3*E3 -> 88.45 | J3: =+D3 -> 61 | K3: =+E3 -> 1.45 | L3: =+F3 -> 88.45 | M3: REGRESAR A FACTURA
C4: =+COMPRAS!G10 -> Bastidor | D4: =+COMPRAS!D10 -> 56.21 | E4: =+COMPRAS!H10 -> 2.96 | F4: =+D4*E4 -> 166.3816 | J4: =+D4 -> 56.21 | K4: =+E4 -> 2.96 | L4: =+F4 -> 166.3816
C5: =+COMPRAS!G11 -> Tira Color Dorado Con Filos Negros De 7.5 Ancho | D5: =+COMPRAS!D11 -> 49 | E5: =+COMPRAS!H11 -> 3.15 | F5: =+D5*E5 -> 154.35 | J5: =+D5 -> 49 | K5: =+E5 -> 3.15 | L5: =+F5 -> 154.35
C6: =+COMPRAS!G12 -> Blanca Estucada Semimate | D6: =+COMPRAS!D12 -> 12.2 | E6: =+COMPRAS!H12 -> 1.25 | F6: =+D6*E6 -> 15.25 | J6: =+D6 -> 12.2 | K6: =+E6 -> 1.25 | L6: =+F6 -> 15.25
A7: =+COMPRAS!C44 -> 43497 | B7: =+CONCATENATE(COMPRAS!C34," ",COMPRAS!C54) -> FACTURA COMPRA # 2 001-001-101 | C7: =+COMPRAS!G37 -> ACEITE DE VASELINA GL.QF | D7: =+COMPRAS!D37 -> 61 | E7: =+COMPRAS!H37 -> 1.45 | F7: =+D7*E7 -> 88.45 | J7: =+J3+D7 -> 122 | K7: =+L7/J7 -> 1.45 | L7: =+L3+F7 -> 176.9 | M7: REGRESAR A FACTURA
C8: =+COMPRAS!G38 -> Bastidor | D8: =+COMPRAS!D38 -> 56.21 | E8: =+COMPRAS!H38 -> 2.96 | F8: =+D8*E8 -> 166.3816 | J8: =+J4+D8 -> 112.42 | K8: =+L8/J8 -> 2.96 | L8: =+L4+F8 -> 332.7632
C9: =+COMPRAS!G39 -> Tira Color Dorado Con Filos Negros De 7.5 Ancho | D9: =+COMPRAS!D39 -> 49 | E9: =+COMPRAS!H39 -> 3.15 | F9: =+D9*E9 -> 154.35 | J9: =+J5+D9 -> 98 | K9: =+L9/J9 -> 3.15 | L9: =+L5+F9 -> 308.7
C10: =+COMPRAS!G40 -> Blanca Estucada Semimate | D10: =+COMPRAS!D40 -> 12.2 | E10: =+COMPRAS!H40 -> 1.25 | F10: =+D10*E10 -> 15.25 | J10: =+J6+D10 -> 24.4 | K10: =+L10/J10 -> 1.25 | L10: =+L6+F10 -> 30.5
A11: =+COMPRAS!C72 -> 43497 | B11: =+CONCATENATE(COMPRAS!C62," ",COMPRAS!C82) -> FACTURA COMPRA # 3 001-001-102 | C11: =+COMPRAS!G65 -> ACEITE DE VASELINA GL.QF | D11: =+COMPRAS!D65 -> 61 | E11: =+COMPRAS!H65 -> 1.45 | F11: =+D11*E11 -> 88.45 | J11: =+J7+D11 -> 183 | K11: =+L11/J11 -> 1.45 | L11: =+L7+F11 -> 265.35 | M11: REGRESAR A FACTURA
C12: =+COMPRAS!G66 -> Bastidor | D12: =+COMPRAS!D66 -> 56.21 | E12: =+COMPRAS!H66 -> 2.96 | F12: =+D12*E12 -> 166.3816 | J12: =+J8+D12 -> 168.63 | K12: =+L12/J12 -> 2.96 | L12: =+L8+F12 -> 499.1448
C13: =+COMPRAS!G67 -> Tira Color Dorado Con Filos Negros De 7.5 Ancho | D13: =+COMPRAS!D67 -> 49 | E13: =+COMPRAS!H67 -> 3.15 | F13: =+D13*E13 -> 154.35 | J13: =+J9+D13 -> 147 | K13: =+L13/J13 -> 3.15 | L13: =+L9+F13 -> 463.05
C14: =+COMPRAS!G68 -> Blanca Estucada Semimate | D14: =+COMPRAS!D68 -> 12.2 | E14: =+COMPRAS!H68 -> 1.25 | F14: =+D14*E14 -> 15.25 | J14: =+J10+D14 -> 36.6 | K14: =+L14/J14 -> 1.25 | L14: =+L10+F14 -> 45.75
A15: =+COMPRAS!C100 -> 43498 | B15: =+CONCATENATE(COMPRAS!C90," ",COMPRAS!C110) -> FACTURA COMPRA # 4 001-001-103 | C15: =+COMPRAS!G93 -> Azúl Con Dorado | D15: =+COMPRAS!D93 -> 118.47 | E15: =+COMPRAS!H93 -> 1.47 | F15: =+D15*E15 -> 174.1509 | J15: =+D15 -> 118.47 | K15: =+E15 -> 1.47 | L15: =+F15 -> 174.1509 | M15: REGRESAR A FACTURA
C16: =+COMPRAS!G94 -> pino natural procesado con ceja izq | D16: =+COMPRAS!D94 -> 249.58 | E16: =+COMPRAS!H94 -> 2.96 | F16: =+D16*E16 -> 738.7568 | J16: =+D16 -> 249.58 | K16: =+E16 -> 2.96 | L16: =+F16 -> 738.7568
C17: =+COMPRAS!G95 -> pino natural peq. Procesado ceja | D17: =+COMPRAS!D95 -> 73.54 | E17: =+COMPRAS!H95 -> 3.15 | F17: =+D17*E17 -> 231.651 | J17: =+D17 -> 73.54 | K17: =+E17 -> 3.15 | L17: =+F17 -> 231.651
C18: =+COMPRAS!G96 -> pino natural procesado con ceja der | D18: =+COMPRAS!D96 -> 29 | E18: =+COMPRAS!H96 -> 1.25 | F18: =+D18*E18 -> 36.25 | J18: =+D18 -> 29 | K18: =+E18 -> 1.25 | L18: =+F18 -> 36.25
A19: =+COMPRAS!C128 -> 43498 | B19: =+CONCATENATE(COMPRAS!C118," ",COMPRAS!C138) -> FACTURA COMPRA # 5 001-001-104 | C19: =+COMPRAS!G121 -> Azúl Con Dorado | D19: =+COMPRAS!D121 -> 118.47 | E19: =+COMPRAS!H121 -> 1.47 | F19: =+D19*E19 -> 174.1509 | J19: =+J15+D19 -> 236.94 | K19: =+L19/J19 -> 1.47 | L19: =+L15+F19 -> 348.3018 | M19: REGRESAR A FACTURA
C20: =+COMPRAS!G122 -> pino natural procesado con ceja izq | D20: =+COMPRAS!D122 -> 249.58 | E20: =+COMPRAS!H122 -> 2.96 | F20: =+D20*E20 -> 738.7568 | J20: =+J16+D20 -> 499.16 | K20: =+L20/J20 -> 2.96 | L20: =+L16+F20 -> 1477.5136
C21: =+COMPRAS!G123 -> pino natural peq. Procesado ceja | D21: =+COMPRAS!D123 -> 73.54 | E21: =+COMPRAS!H123 -> 3.15 | F21: =+D21*E21 -> 231.651 | J21: =+J17+D21 -> 147.08 | K21: =+L21/J21 -> 3.15 | L21: =+L17+F21 -> 463.302
C22: =+COMPRAS!G124 -> pino natural procesado con ceja der | D22: =+COMPRAS!D124 -> 29 | E22: =+COMPRAS!H124 -> 1.25 | F22: =+D22*E22 -> 36.25 | J22: =+J18+D22 -> 58 | K22: =+L22/J22 -> 1.25 | L22: =+L18+F22 -> 72.5
A23: =+COMPRAS!C161 -> 43498 | B23: =+CONCATENATE(COMPRAS!C151," ",COMPRAS!C171) -> FACTURA COMPRA # 6 001-001-105 | C23: =+COMPRAS!G154 -> Azúl Con Dorado | D23: =+COMPRAS!D154 -> 118.47 | E23: =+COMPRAS!H154 -> 1.47 | F23: =+D23*E23 -> 174.1509 | J23: =+J19+D23 -> 355.41 | K23: =+L23/J23 -> 1.47 | L23: =+L19+F23 -> 522.4527 | M23: REGRESAR A FACTURA
C24: =+COMPRAS!G155 -> pino natural procesado con ceja izq | D24: =+COMPRAS!D155 -> 249.58 | E24: =+COMPRAS!H155 -> 2.96 | F24: =+D24*E24 -> 738.7568 | J24: =+J20+D24 -> 748.74 | K24: =+L24/J24 -> 2.96 | L24: =+L20+F24 -> 2216.2704
C25: =+COMPRAS!G156 -> pino natural peq. Procesado ceja | D25: =+COMPRAS!D156 -> 73.54 | E25: =+COMPRAS!H156 -> 3.15 | F25: =+D25*E25 -> 231.651 | J25: =+J21+D25 -> 220.62 | K25: =+L25/J25 -> 3.15 | L25: =+L21+F25 -> 694.953
C26: =+COMPRAS!G157 -> pino natural procesado con ceja der | D26: =+COMPRAS!D157 -> 29 | E26: =+COMPRAS!H157 -> 1.25 | F26: =+D26*E26 -> 36.25 | J26: =+J22+D26 -> 87 | K26: =+L26/J26 -> 1.25 | L26: =+L22+F26 -> 108.75
A27: =+COMPRAS!C192 -> 43497 | B27: =+CONCATENATE(COMPRAS!C182," ",COMPRAS!C193,"-",COMPRAS!C194,"-",COMPRAS!C195) -> FACTURA COMPRA # 7 001-001-106 | C27: =+COMPRAS!G185 -> ACEITE DE VASELINA GL.QF | D27: =+COMPRAS!D185 -> 61 | E27: =+COMPRAS!H185 -> 1.45 | F27: =+D27*E27 -> 88.45 | J27: =+J11+D27 -> 244 | K27: =+L27/J27 -> 1.45 | L27: =+L11+F27 -> 353.8 | M27: REGRESAR A FACTURA
C28: =+COMPRAS!G186 -> Bastidor | D28: =+COMPRAS!D186 -> 56.21 | E28: =+COMPRAS!H186 -> 2.96 | F28: =+D28*E28 -> 166.3816 | J28: =+J12+D28 -> 224.84 | K28: =+L28/J28 -> 2.96 | L28: =+L12+F28 -> 665.5264
C29: =+COMPRAS!G187 -> Tira Color Dorado Con Filos Negros De 7.5 Ancho | D29: =+COMPRAS!D187 -> 49 | E29: =+COMPRAS!H187 -> 3.15 | F29: =+D29*E29 -> 154.35 | J29: =+J13+D29 -> 196 | K29: =+L29/J29 -> 3.15 | L29: =+L13+F29 -> 617.4
C30: =+COMPRAS!G188 -> Blanca Estucada Semimate | D30: =+COMPRAS!D188 -> 12.2 | E30: =+COMPRAS!H188 -> 1.25 | F30: =+D30*E30 -> 15.25 | J30: =+J14+D30 -> 48.8 | K30: =+L30/J30 -> 1.25 | L30: =+L14+F30 -> 61
A31: =+COMPRAS!C215 -> 43497 | B31: =+CONCATENATE(COMPRAS!C205," ",COMPRAS!C216,"-",COMPRAS!C217,"-",COMPRAS!C218) -> FACTURA COMPRA # 8 001-001-107 | C31: =+COMPRAS!G208 -> ACEITE DE VASELINA GL.QF | D31: =+COMPRAS!D208 -> 61 | E31: =+COMPRAS!H208 -> 1.45 | F31: =+D31*E31 -> 88.45 | J31: =+J27+D31 -> 305 | K31: =+L31/J31 -> 1.45 | L31: =+L27+F31 -> 442.25 | M31: REGRESAR A FACTURA
C32: =+COMPRAS!G209 -> Bastidor | D32: =+COMPRAS!D209 -> 56.21 | E32: =+COMPRAS!H209 -> 2.96 | F32: =+D32*E32 -> 166.3816 | J32: =+J28+D32 -> 281.05 | K32: =+L32/J32 -> 2.96 | L32: =+L28+F32 -> 831.908
C33: =+COMPRAS!G210 -> Tira Color Dorado Con Filos Negros De 7.5 Ancho | D33: =+COMPRAS!D210 -> 49 | E33: =+COMPRAS!H210 -> 4.73 | F33: =+D33*E33 -> 231.77 | J33: =+J29+D33 -> 245 | K33: =+L33/J33 -> 3.466 | L33: =+L29+F33 -> 849.17
C34: =+COMPRAS!G211 -> Blanca Estucada Semimate | D34: =+COMPRAS!D211 -> 12.2 | E34: =+COMPRAS!H211 -> 1.25 | F34: =+D34*E34 -> 15.25 | J34: =+J30+D34 -> 61 | K34: =+L34/J34 -> 1.25 | L34: =+L30+F34 -> 76.25
A35: =+COMPRAS!C238 -> 43497 | B35: =+CONCATENATE(COMPRAS!C228," ",COMPRAS!C239,"-",COMPRAS!C240,"-",COMPRAS!C241) -> FACTURA COMPRA # 9 001-001-108 | C35: =+COMPRAS!G231 -> ACEITE DE VASELINA GL.QF | D35: =+COMPRAS!D231 -> 61 | E35: =+COMPRAS!H231 -> 1.45 | F35: =+D35*E35 -> 88.45 | J35: =+J31+D35 -> 366 | K35: =+L35/J35 -> 1.45 | L35: =+L31+F35 -> 530.7 | M35: REGRESAR A FACTURA
C36: =+COMPRAS!G232 -> Bastidor | D36: =+COMPRAS!D232 -> 56.21 | E36: =+COMPRAS!H232 -> 2.96 | F36: =+D36*E36 -> 166.3816 | J36: =+J32+D36 -> 337.26 | K36: =+L36/J36 -> 2.96 | L36: =+L32+F36 -> 998.2896
C37: =+COMPRAS!G233 -> Tira Color Dorado Con Filos Negros De 7.5 Ancho | D37: =+COMPRAS!D233 -> 49 | E37: =+COMPRAS!H233 -> 2.77 | F37: =+D37*E37 -> 135.73 | J37: =+J33+D37 -> 294 | K37: =+L37/J37 -> 3.35 | L37: =+L33+F37 -> 984.9
C38: =+COMPRAS!G234 -> Blanca Estucada Semimate | D38: =+COMPRAS!D234 -> 12.2 | E38: =+COMPRAS!H234 -> 1.25 | F38: =+D38*E38 -> 15.25 | J38: =+J34+D38 -> 73.2 | K38: =+L38/J38 -> 1.25 | L38: =+L34+F38 -> 91.5
A39: =+COMPRAS!C261 -> 43498 | B39: =+CONCATENATE(COMPRAS!C251," ",COMPRAS!C262,"-",COMPRAS!C263,"-",COMPRAS!C264) -> FACTURA COMPRA # 10 001-001-109 | C39: =+COMPRAS!G254 -> Azúl Con Dorado | D39: =+COMPRAS!D254 -> 118.47 | E39: =+COMPRAS!H254 -> 1.47 | F39: =+D39*E39 -> 174.1509 | J39: =+J23+D39 -> 473.88 | K39: =+L39/J39 -> 1.47 | L39: =+L23+F39 -> 696.6036 | M39: REGRESAR A FACTURA
C40: =+COMPRAS!G255 -> pino natural procesado con ceja izq | D40: =+COMPRAS!D255 -> 249.58 | E40: =+COMPRAS!H255 -> 2.96 | F40: =+D40*E40 -> 738.7568 | J40: =+J24+D40 -> 998.32 | K40: =+L40/J40 -> 2.96 | L40: =+L24+F40 -> 2955.0272
C41: =+COMPRAS!G256 -> pino natural peq. Procesado ceja | D41: =+COMPRAS!D256 -> 73.54 | E41: =+COMPRAS!H256 -> 3.15 | F41: =+D41*E41 -> 231.651 | J41: =+J25+D41 -> 294.16 | K41: =+L41/J41 -> 3.15 | L41: =+L25+F41 -> 926.604
C42: =+COMPRAS!G257 -> pino natural procesado con ceja der | D42: =+COMPRAS!D257 -> 29 | E42: =+COMPRAS!H257 -> 1.25 | F42: =+D42*E42 -> 36.25 | J42: =+J26+D42 -> 116 | K42: =+L42/J42 -> 1.25 | L42: =+L26+F42 -> 145
A43: =+COMPRAS!C284 -> 43498 | B43: =+CONCATENATE(COMPRAS!C274," ",COMPRAS!C285,"-",COMPRAS!C286,"-",COMPRAS!C287) -> FACTURA COMPRA # 11 001-001-110 | C43: =+COMPRAS!G277 -> Azúl Con Dorado | D43: =+COMPRAS!D277 -> 118.47 | E43: =+COMPRAS!H277 -> 1.47 | F43: =+D43*E43 -> 174.1509 | J43: =+J39+D43 -> 592.35 | K43: =+L43/J43 -> 1.47 | L43: =+L39+F43 -> 870.7545 | M43: REGRESAR A FACTURA
C44: =+COMPRAS!G278 -> pino natural procesado con ceja izq | D44: =+COMPRAS!D278 -> 249.58 | E44: =+COMPRAS!H278 -> 2.96 | F44: =+D44*E44 -> 738.7568 | J44: =+J40+D44 -> 1247.9 | K44: =+L44/J44 -> 2.96 | L44: =+L40+F44 -> 3693.784
C45: =+COMPRAS!G279 -> pino natural peq. Procesado ceja | D45: =+COMPRAS!D279 -> 73.54 | E45: =+COMPRAS!H279 -> 3.15 | F45: =+D45*E45 -> 231.651 | J45: =+J41+D45 -> 367.7 | K45: =+L45/J45 -> 3.15 | L45: =+L41+F45 -> 1158.255
C46: =+COMPRAS!G280 -> pino natural procesado con ceja der | D46: =+COMPRAS!D280 -> 29 | E46: =+COMPRAS!H280 -> 1.25 | F46: =+D46*E46 -> 36.25 | J46: =+J42+D46 -> 145 | K46: =+L46/J46 -> 1.25 | L46: =+L42+F46 -> 181.25
A47: =+COMPRAS!C313 -> 43498 | B47: =+CONCATENATE(COMPRAS!C303," ",COMPRAS!C314,"-",COMPRAS!C315,"-",COMPRAS!C316) -> FACTURA COMPRA # 12 001-001-111 | C47: =+COMPRAS!G306 -> Azúl Con Dorado | D47: =+COMPRAS!D306 -> 118.47 | E47: =+COMPRAS!H306 -> 1.47 | F47: =+D47*E47 -> 174.1509 | J47: =+J43+D47 -> 710.82 | K47: =+L47/J47 -> 1.47 | L47: =+L43+F47 -> 1044.9054 | M47: REGRESAR A FACTURA
C48: =+COMPRAS!G307 -> pino natural procesado con ceja izq | D48: =+COMPRAS!D307 -> 249.58 | E48: =+COMPRAS!H307 -> 2.96 | F48: =+D48*E48 -> 738.7568 | J48: =+J44+D48 -> 1497.48 | K48: =+L48/J48 -> 2.96 | L48: =+L44+F48 -> 4432.5408
C49: =+COMPRAS!G308 -> pino natural peq. Procesado ceja | D49: =+COMPRAS!D308 -> 73.54 | E49: =+COMPRAS!H308 -> 3.15 | F49: =+D49*E49 -> 231.651 | J49: =+J45+D49 -> 441.24 | K49: =+L49/J49 -> 3.15 | L49: =+L45+F49 -> 1389.906
C50: =+COMPRAS!G309 -> pino natural procesado con ceja der | D50: =+COMPRAS!D309 -> 29 | E50: =+COMPRAS!H309 -> 1.25 | F50: =+D50*E50 -> 36.25 | J50: =+J46+D50 -> 174 | K50: =+L50/J50 -> 1.25 | L50: =+L46+F50 -> 217.5
A51: =+COMPRAS!C662 -> 43504 | B51: =+CONCATENATE(COMPRAS!C652," ",COMPRAS!C663,"-",COMPRAS!C664,"-",COMPRAS!C665) -> FACTURA COMPRA # 25 001-001-120 | C51: =+COMPRAS!G655 -> ACEITE DE VASELINA GL.QF | D51: =+COMPRAS!D655 -> 61 | E51: =+COMPRAS!H655 -> 1.45 | F51: =+D51*E51 -> 88.45 | J51: =+J35+D51 -> 427 | K51: =+L51/J51 -> 1.45 | L51: =+L35+F51 -> 619.15 | M51: REGRESAR A FACTURA
C52: =+COMPRAS!G656 -> Bastidor | D52: =+COMPRAS!D656 -> 56.21 | E52: =+COMPRAS!H656 -> 2.96 | F52: =+D52*E52 -> 166.3816 | J52: =+J36+D52 -> 393.47 | K52: =+L52/J52 -> 2.96 | L52: =+L36+F52 -> 1164.6712
C53: =+COMPRAS!G657 -> Tira Color Dorado Con Filos Negros De 7.5 Ancho | D53: =+COMPRAS!D657 -> 49 | E53: =+COMPRAS!H657 -> 3.15 | F53: =+D53*E53 -> 154.35 | J53: =+J37+D53 -> 343 | K53: =+L53/J53 -> 3.3214286 | L53: =+L37+F53 -> 1139.25
C54: =+COMPRAS!G658 -> Blanca Estucada Semimate | D54: =+COMPRAS!D658 -> 12.2 | E54: =+COMPRAS!H658 -> 1.25 | F54: =+D54*E54 -> 15.25 | J54: =+J38+D54 -> 85.4 | K54: =+L54/J54 -> 1.25 | L54: =+L38+F54 -> 106.75
A55: =+COMPRAS!C690 -> 43504 | B55: =+CONCATENATE(COMPRAS!C680," ",COMPRAS!C691,"-",COMPRAS!C692,"-",COMPRAS!C693) -> FACTURA COMPRA # 26 001-001-121 | C55: =+COMPRAS!G683 -> ACEITE DE VASELINA GL.QF | D55: =+COMPRAS!D683 -> 61 | E55: =+COMPRAS!H683 -> 1.45 | F55: =+D55*E55 -> 88.45 | J55: =+J51+D55 -> 488 | K55: =+L55/J55 -> 1.45 | L55: =+L51+F55 -> 707.6 | M55: REGRESAR A FACTURA
C56: =+COMPRAS!G684 -> Bastidor | D56: =+COMPRAS!D684 -> 56.21 | E56: =+COMPRAS!H684 -> 2.96 | F56: =+D56*E56 -> 166.3816 | J56: =+J52+D56 -> 449.68 | K56: =+L56/J56 -> 2.96 | L56: =+L52+F56 -> 1331.0528
C57: =+COMPRAS!G685 -> Tira Color Dorado Con Filos Negros De 7.5 Ancho | D57: =+COMPRAS!D685 -> 49 | E57: =+COMPRAS!H685 -> 3.15 | F57: =+D57*E57 -> 154.35 | J57: =+J53+D57 -> 392 | K57: =+L57/J57 -> 3.3 | L57: =+L53+F57 -> 1293.6
C58: =+COMPRAS!G686 -> Blanca Estucada Semimate | D58: =+COMPRAS!D686 -> 12.2 | E58: =+COMPRAS!H686 -> 1.25 | F58: =+D58*E58 -> 15.25 | J58: =+J54+D58 -> 97.6 | K58: =+L58/J58 -> 1.25 | L58: =+L54+F58 -> 122
A59: =+COMPRAS!C718 -> 43504 | B59: =+CONCATENATE(COMPRAS!C708," ",COMPRAS!C719,"-",COMPRAS!C720,"-",COMPRAS!C721) -> FACTURA COMPRA # 27 001-001-122 | C59: =+COMPRAS!G711 -> ACEITE DE VASELINA GL.QF | D59: =+COMPRAS!D711 -> 61 | E59: =+COMPRAS!H711 -> 1.45 | F59: =+D59*E59 -> 88.45 | J59: =+J55+D59 -> 549 | K59: =+L59/J59 -> 1.45 | L59: =+L55+F59 -> 796.05 | M59: REGRESAR A FACTURA
C60: =+COMPRAS!G712 -> Bastidor | D60: =+COMPRAS!D712 -> 56.21 | E60: =+COMPRAS!H712 -> 2.96 | F60: =+D60*E60 -> 166.3816 | J60: =+J56+D60 -> 505.89 | K60: =+L60/J60 -> 2.96 | L60: =+L56+F60 -> 1497.4344
C61: =+COMPRAS!G713 -> Tira Color Dorado Con Filos Negros De 7.5 Ancho | D61: =+COMPRAS!D713 -> 49 | E61: =+COMPRAS!H713 -> 3.15 | F61: =+D61*E61 -> 154.35 | J61: =+J57+D61 -> 441 | K61: =+L61/J61 -> 3.2833333 | L61: =+L57+F61 -> 1447.95
C62: =+COMPRAS!G714 -> Blanca Estucada Semimate | D62: =+COMPRAS!D714 -> 12.2 | E62: =+COMPRAS!H714 -> 1.25 | F62: =+D62*E62 -> 15.25 | J62: =+J58+D62 -> 109.8 | K62: =+L62/J62 -> 1.25 | L62: =+L58+F62 -> 137.25
A63: =+COMPRAS!C746 -> 43505 | B63: =+CONCATENATE(COMPRAS!C736," ",COMPRAS!C747,"-",COMPRAS!C748,"-",COMPRAS!C749) -> FACTURA COMPRA # 28 001-001-123 | C63: =+COMPRAS!G739 -> Azúl Con Dorado | D63: =+COMPRAS!D739 -> 118.47 | E63: =+COMPRAS!H739 -> 1.47 | F63: =+D63*E63 -> 174.1509 | J63: =+J47+D63 -> 829.29 | K63: =+L63/J63 -> 1.47 | L63: =+L47+F63 -> 1219.0563 | M63: REGRESAR A FACTURA
C64: =+COMPRAS!G740 -> pino natural procesado con ceja izq | D64: =+COMPRAS!D740 -> 249.58 | E64: =+COMPRAS!H740 -> 2.96 | F64: =+D64*E64 -> 738.7568 | J64: =+J48+D64 -> 1747.06 | K64: =+L64/J64 -> 2.96 | L64: =+L48+F64 -> 5171.2976
C65: =+COMPRAS!G741 -> pino natural peq. Procesado ceja | D65: =+COMPRAS!D741 -> 73.54 | E65: =+COMPRAS!H741 -> 3.15 | F65: =+D65*E65 -> 231.651 | J65: =+J49+D65 -> 514.78 | K65: =+L65/J65 -> 3.15 | L65: =+L49+F65 -> 1621.557
C66: =+COMPRAS!G742 -> pino natural procesado con ceja der | D66: =+COMPRAS!D742 -> 29 | E66: =+COMPRAS!H742 -> 1.25 | F66: =+D66*E66 -> 36.25 | J66: =+J50+D66 -> 203 | K66: =+L66/J66 -> 1.25 | L66: =+L50+F66 -> 253.75
A67: =+COMPRAS!C774 -> 43505 | B67: =+CONCATENATE(COMPRAS!C764," ",COMPRAS!C775,"-",COMPRAS!C776,"-",COMPRAS!C777) -> FACTURA COMPRA # 29 001-001-124 | C67: =+COMPRAS!G767 -> Azúl Con Dorado | D67: =+COMPRAS!D767 -> 118.47 | E67: =+COMPRAS!H767 -> 1.47 | F67: =+D67*E67 -> 174.1509 | J67: =+J63+D67 -> 947.76 | K67: =+L67/J67 -> 1.47 | L67: =+L63+F67 -> 1393.2072 | M67: REGRESAR A FACTURA
C68: =+COMPRAS!G768 -> pino natural procesado con ceja izq | D68: =+COMPRAS!D768 -> 249.58 | E68: =+COMPRAS!H768 -> 2.96 | F68: =+D68*E68 -> 738.7568 | J68: =+J64+D68 -> 1996.64 | K68: =+L68/J68 -> 2.96 | L68: =+L64+F68 -> 5910.0544
C69: =+COMPRAS!G769 -> pino natural peq. Procesado ceja | D69: =+COMPRAS!D769 -> 73.54 | E69: =+COMPRAS!H769 -> 3.15 | F69: =+D69*E69 -> 231.651 | J69: =+J65+D69 -> 588.32 | K69: =+L69/J69 -> 3.15 | L69: =+L65+F69 -> 1853.208
C70: =+COMPRAS!G770 -> pino natural procesado con ceja der | D70: =+COMPRAS!D770 -> 29 | E70: =+COMPRAS!H770 -> 1.25 | F70: =+D70*E70 -> 36.25 | J70: =+J66+D70 -> 232 | K70: =+L70/J70 -> 1.25 | L70: =+L66+F70 -> 290
A71: =+COMPRAS!C807 -> 43505 | B71: =+CONCATENATE(COMPRAS!C797," ",COMPRAS!C808,"-",COMPRAS!C809,"-",COMPRAS!C810) -> FACTURA COMPRA # 30 001-001-125 | C71: =+COMPRAS!G800 -> Azúl Con Dorado | D71: =+COMPRAS!D800 -> 118.47 | E71: =+COMPRAS!H800 -> 1.47 | F71: =+D71*E71 -> 174.1509 | J71: =+J67+D71 -> 1066.23 | K71: =+L71/J71 -> 1.47 | L71: =+L67+F71 -> 1567.3581 | M71: REGRESAR A FACTURA
C72: =+COMPRAS!G801 -> pino natural procesado con ceja izq | D72: =+COMPRAS!D801 -> 249.58 | E72: =+COMPRAS!H801 -> 2.96 | F72: =+D72*E72 -> 738.7568 | J72: =+J68+D72 -> 2246.22 | K72: =+L72/J72 -> 2.96 | L72: =+L68+F72 -> 6648.8112
C73: =+COMPRAS!G802 -> pino natural peq. Procesado ceja | D73: =+COMPRAS!D802 -> 73.54 | E73: =+COMPRAS!H802 -> 3.15 | F73: =+D73*E73 -> 231.651 | J73: =+J69+D73 -> 661.86 | K73: =+L73/J73 -> 3.15 | L73: =+L69+F73 -> 2084.859
C74: =+COMPRAS!G803 -> pino natural procesado con ceja der | D74: =+COMPRAS!D803 -> 29 | E74: =+COMPRAS!H803 -> 1.25 | F74: =+D74*E74 -> 36.25 | J74: =+J70+D74 -> 261 | K74: =+L74/J74 -> 1.25 | L74: =+L70+F74 -> 326.25
A75: =+COMPRAS!C838 -> 43510 | B75: =+CONCATENATE(COMPRAS!C828," ",COMPRAS!C839,"-",COMPRAS!C840,"-",COMPRAS!C841) -> FACTURA COMPRA # 31 002-902-000220795 | C75: =+COMPRAS!G831 -> Resistencia duchas 5 12v / gasto febrero mantenimiento | D75: =+COMPRAS!D831 -> 1 | E75: =+COMPRAS!H831 -> 5.89 | F75: =+D75*E75 -> 5.89 | J75: =+J59+D75 -> 550 | K75: =+L75/J75 -> 1.4580727 | L75: =+L59+F75 -> 801.94 | M75: REGRESAR A FACTURA
C76: =+COMPRAS!G832 -> Identificador Circular / gasto febrero mantenimiento | D76: =+COMPRAS!D832 -> 19 | E76: =+COMPRAS!H832 -> 0.285714 | F76: =+D76*E76 -> 5.428566 | J76: =+J60+D76 -> 524.89 | K76: =+L76/J76 -> 2.863196 | L76: =+L60+F76 -> 1502.863
C77: =+COMPRAS!G833 -> Aro p 1-1/2 / gasto febrero mantenimiento | D77: =+COMPRAS!D833 -> 2 | E77: =+COMPRAS!H833 -> 1.3839 | F77: =+D77*E77 -> 2.7678 | J77: =+J61+D77 -> 443 | K77: =+L77/J77 -> 3.274758 | L77: =+L61+F77 -> 1450.7178
C78: =+COMPRAS!G834 -> 0 | D78: =+COMPRAS!D834 -> 0 | E78: =+COMPRAS!H834 -> 0 | F78: =+D78*E78 -> 0 | J78: =+J62+D78 -> 109.8 | K78: =+L78/J78 -> 1.25 | L78: =+L62+F78 -> 137.25
A79: =+COMPRAS!C861 -> 43510 | B79: =+CONCATENATE(COMPRAS!C851," ",COMPRAS!C862,"-",COMPRAS!C863,"-",COMPRAS!C864) -> FACTURA COMPRA # 32 001-001-127 | C79: =+COMPRAS!G854 -> ACEITE DE VASELINA GL.QF | D79: =+COMPRAS!D854 -> 61 | E79: =+COMPRAS!H854 -> 1.45 | F79: =+D79*E79 -> 88.45 | J79: =+J75+D79 -> 611 | K79: =+L79/J79 -> 1.4572668 | L79: =+L75+F79 -> 890.39 | M79: REGRESAR A FACTURA
C80: =+COMPRAS!G855 -> Bastidor | D80: =+COMPRAS!D855 -> 56.21 | E80: =+COMPRAS!H855 -> 2.96 | F80: =+D80*E80 -> 166.3816 | J80: =+J76+D80 -> 581.1 | K80: =+L80/J80 -> 2.8725599 | L80: =+L76+F80 -> 1669.2446
C81: =+COMPRAS!G856 -> Tira Color Dorado Con Filos Negros De 7.5 Ancho | D81: =+COMPRAS!D856 -> 49 | E81: =+COMPRAS!H856 -> 3.15 | F81: =+D81*E81 -> 154.35 | J81: =+J77+D81 -> 492 | K81: =+L81/J81 -> 3.2623329 | L81: =+L77+F81 -> 1605.0678
C82: =+COMPRAS!G857 -> Blanca Estucada Semimate | D82: =+COMPRAS!D857 -> 12.2 | E82: =+COMPRAS!H857 -> 1.25 | F82: =+D82*E82 -> 15.25 | J82: =+J78+D82 -> 122 | K82: =+L82/J82 -> 1.25 | L82: =+L78+F82 -> 152.5
A83: =+COMPRAS!C884 -> 43510 | B83: =+CONCATENATE(COMPRAS!C874," ",COMPRAS!C885,"-",COMPRAS!C886,"-",COMPRAS!C887) -> FACTURA COMPRA # 33 001-001-128 | C83: =+COMPRAS!G877 -> ACEITE DE VASELINA GL.QF | D83: =+COMPRAS!D877 -> 61 | E83: =+COMPRAS!H877 -> 1.45 | F83: =+D83*E83 -> 88.45 | J83: =+J79+D83 -> 672 | K83: =+L83/J83 -> 1.4566071 | L83: =+L79+F83 -> 978.84 | M83: REGRESAR A FACTURA
C84: =+COMPRAS!G878 -> Bastidor | D84: =+COMPRAS!D878 -> 56.21 | E84: =+COMPRAS!H878 -> 2.96 | F84: =+D84*E84 -> 166.3816 | J84: =+J80+D84 -> 637.31 | K84: =+L84/J84 -> 2.880272 | L84: =+L80+F84 -> 1835.6262
C85: =+COMPRAS!G879 -> Tira Color Dorado Con Filos Negros De 7.5 Ancho | D85: =+COMPRAS!D879 -> 49 | E85: =+COMPRAS!H879 -> 3.15 | F85: =+D85*E85 -> 154.35 | J85: =+J81+D85 -> 541 | K85: =+L85/J85 -> 3.2521586 | L85: =+L81+F85 -> 1759.4178
C86: =+COMPRAS!G880 -> Blanca Estucada Semimate | D86: =+COMPRAS!D880 -> 12.2 | E86: =+COMPRAS!H880 -> 1.25 | F86: =+D86*E86 -> 15.25 | J86: =+J82+D86 -> 134.2 | K86: =+L86/J86 -> 1.25 | L86: =+L82+F86 -> 167.75
A87: =+COMPRAS!C907 -> 43510 | B87: =+CONCATENATE(COMPRAS!C897," ",COMPRAS!C908,"-",COMPRAS!C909,"-",COMPRAS!C910) -> FACTURA COMPRA # 34 001-001-129 | C87: =+COMPRAS!G900 -> Azúl Con Dorado | D87: =+COMPRAS!D900 -> 118.47 | E87: =+COMPRAS!H900 -> 1.47 | F87: =+D87*E87 -> 174.1509 | J87: =+J71+D87 -> 1184.7 | K87: =+L87/J87 -> 1.47 | L87: =+L71+F87 -> 1741.509 | M87: REGRESAR A FACTURA
C88: =+COMPRAS!G901 -> pino natural procesado con ceja izq | D88: =+COMPRAS!D901 -> 249.58 | E88: =+COMPRAS!H901 -> 2.96 | F88: =+D88*E88 -> 738.7568 | J88: =+J72+D88 -> 2495.8 | K88: =+L88/J88 -> 2.96 | L88: =+L72+F88 -> 7387.568
C89: =+COMPRAS!G902 -> pino natural peq. Procesado ceja | D89: =+COMPRAS!D902 -> 73.54 | E89: =+COMPRAS!H902 -> 3.15 | F89: =+D89*E89 -> 231.651 | J89: =+J73+D89 -> 735.4 | K89: =+L89/J89 -> 3.15 | L89: =+L73+F89 -> 2316.51
C90: =+COMPRAS!G903 -> pino natural procesado con ceja der | D90: =+COMPRAS!D903 -> 29 | E90: =+COMPRAS!H903 -> 1.25 | F90: =+D90*E90 -> 36.25 | J90: =+J74+D90 -> 290 | K90: =+L90/J90 -> 1.25 | L90: =+L74+F90 -> 362.5
A91: =+COMPRAS!C930 -> 43510 | B91: =+CONCATENATE(COMPRAS!C920," ",COMPRAS!C931,"-",COMPRAS!C932,"-",COMPRAS!C933) -> FACTURA COMPRA # 35 001-001-130 | C91: =+COMPRAS!G923 -> Azúl Con Dorado | D91: =+COMPRAS!D923 -> 118.47 | E91: =+COMPRAS!H923 -> 1.47 | F91: =+D91*E91 -> 174.1509 | J91: =+J87+D91 -> 1303.17 | K91: =+L91/J91 -> 1.47 | L91: =+L87+F91 -> 1915.6599 | M91: REGRESAR A FACTURA
C92: =+COMPRAS!G924 -> pino natural procesado con ceja izq | D92: =+COMPRAS!D924 -> 249.58 | E92: =+COMPRAS!H924 -> 2.96 | F92: =+D92*E92 -> 738.7568 | J92: =+J88+D92 -> 2745.38 | K92: =+L92/J92 -> 2.96 | L92: =+L88+F92 -> 8126.3248
C93: =+COMPRAS!G925 -> pino natural peq. Procesado ceja | D93: =+COMPRAS!D925 -> 73.54 | E93: =+COMPRAS!H925 -> 3.15 | F93: =+D93*E93 -> 231.651 | J93: =+J89+D93 -> 808.94 | K93: =+L93/J93 -> 3.15 | L93: =+L89+F93 -> 2548.161
C94: =+COMPRAS!G926 -> pino natural procesado con ceja der | D94: =+COMPRAS!D926 -> 29 | E94: =+COMPRAS!H926 -> 1.25 | F94: =+D94*E94 -> 36.25 | J94: =+J90+D94 -> 319 | K94: =+L94/J94 -> 1.25 | L94: =+L90+F94 -> 398.75
A95: =+COMPRAS!C958 -> 43510 | B95: =+CONCATENATE(COMPRAS!C948," ",COMPRAS!C959,"-",COMPRAS!C960,"-",COMPRAS!C961) -> FACTURA COMPRA # 36 001-001-131 | C95: =+COMPRAS!G951 -> Azúl Con Dorado | D95: =+COMPRAS!D951 -> 118.47 | E95: =+COMPRAS!H951 -> 1.47 | F95: =+D95*E95 -> 174.1509 | J95: =+J91+D95 -> 1421.64 | K95: =+L95/J95 -> 1.47 | L95: =+L91+F95 -> 2089.8108 | M95: REGRESAR A FACTURA
C96: =+COMPRAS!G952 -> pino natural procesado con ceja izq | D96: =+COMPRAS!D952 -> 249.58 | E96: =+COMPRAS!H952 -> 2.96 | F96: =+D96*E96 -> 738.7568 | J96: =+J92+D96 -> 2994.96 | K96: =+L96/J96 -> 2.96 | L96: =+L92+F96 -> 8865.0816
C97: =+COMPRAS!G953 -> pino natural peq. Procesado ceja | D97: =+COMPRAS!D953 -> 73.54 | E97: =+COMPRAS!H953 -> 3.15 | F97: =+D97*E97 -> 231.651 | J97: =+J93+D97 -> 882.48 | K97: =+L97/J97 -> 3.15 | L97: =+L93+F97 -> 2779.812
C98: =+COMPRAS!G954 -> pino natural procesado con ceja der | D98: =+COMPRAS!D954 -> 29 | E98: =+COMPRAS!H954 -> 1.25 | F98: =+D98*E98 -> 36.25 | J98: =+J94+D98 -> 348 | K98: =+L98/J98 -> 1.25 | L98: =+L94+F98 -> 435
A99: =+VENTAS!C15 -> 43513 | B99: =+CONCATENATE(VENTAS!C6," ",VENTAS!C15,"-",VENTAS!C16,"-",VENTAS!C17) -> FACTURA VENTA # 1 43513-001-001 | C99: =+VENTAS!G9 -> ACEITE DE VASELINA GL.QF | G99: =+VENTAS!D9 -> 15 | H99: =+K83 -> 1.4566071 | I99: =+G99*H99 -> 21.849107 | J99: =+J83-G99 -> 657 | K99: =+H99 -> 1.4566071 | L99: =+L83-I99 -> 956.99089 | M99: REGRESAR A FACTURA
C100: =+VENTAS!G10 -> Bastidor | G100: =+VENTAS!D10 -> 12.37 | H100: =+K84 -> 2.880272 | I100: =+G100*H100 -> 35.628965 | J100: =+J84-G100 -> 624.94 | K100: =+H100 -> 2.880272 | L100: =+L84-I100 -> 1799.9972
...
